{"districts": {"AK": {"s": 0, "p1": 1, "d1": 2, "r1": 3, "i1": 4, "p2": 1, "d2": 5, "r2": 6, "i2": 4, "p3": 1, "d3": 5, "r3": 6, "i3": 4, "o1": 4, "o2": 7, "o3": 7, "o4": 7}, "AL": {"s": 8, "p1": 9, "d1": 10, "r1": 11, "i1": 11, "p2": 9, "d2": 5, "r2": 6, "i2": 11, "p3": 9, "d3": 5, "r3": 6, "i3": 11, "o1": 12, "o2": 13, "o3": 14, "o4": 7}, "AR": {"s": 15, "p1": 9, "d1": 16, "r1": 17, "i1": 17, "p2": 9, "d2": 5, "r2": 6, "i2": 17, "p3": 9, "d3": 5, "r3": 6, "i3": 17, "o1": 18, "o2": 7, "o3": 7, "o4": 7}, "AZ": {"s": 19, "p1": 9, "d1": 20, "r1": 21, "i1": 21, "p2": 9, "d2": 5, "r2": 6, "i2": 21, "p3": 9, "d3": 5, "r3": 6, "i3": 21, "o1": 22, "o2": 23, "o3": 7, "o4": 7}, "CA": {"s": 24, "p1": 25, "d1": 26, "r1": 27, "i1": 28, "p2": 25, "d2": 5, "r2": 6, "i2": 28, "p3": 25, "d3": 5, "r3": 6, "i3": 28, "o1": 7, "o2": 7, "o3": 7, "o4": 7}, "CO": {"s": 29, "p1": 25, "d1": 30, "r1": 31, "i1": 32, "p2": 25, "d2": 5, "r2": 6, "i2": 32, "p3": 25, "d3": 5, "r3": 6, "i3": 32, "o1": 33, "o2": 7, "o3": 34, "o4": 7}, "CT": {"s": 35, "p1": 25, "d1": 36, "r1": 37, "i1": 38, "p2": 25, "d2": 5, "r2": 6, "i2": 38, "p3": 25, "d3": 5, "r3": 6, "i3": 38, "o1": 39, "o2": 40, "o3": 41, "o4": 7}, "DE": {"s": 42, "p4": 25, "d4": 43, "r4": 44, "i4": 43, "p5": 25, "d5": 5, "r5": 45, "i5": 43, "p6": 25, "d6": 5, "r6": 46, "i6": 43, "p7": 25, "d7": 5, "r7": 47, "i7": 43, "p8": 25, "d8": 5, "r8": 44, "i8": 43, "o1": 7, "o2": 7, "o3": 7, "o4": 7}, "FL": {"s": 48, "p1": 9, "d1": 49, "r1": 50, "i1": 51, "p2": 9, "d2": 5, "r2": 6, "i2": 51, "p3": 9, "d3": 5, "r3": 6, "i3": 51, "o1": 52, "o2": 53, "o3": 54, "o4": 7}, "GA": {"s": 55, "p1": 9, "d1": 56, "r1": 57, "i1": 58, "p2": 9, "d2": 5, "r2": 6, "i2": 58, "p3": 9, "d3": 5, "r3": 6, "i3": 58, "o1": 59, "o2": 7, "o3": 7, "o4": 7}, "HI": {"s": 60, "p1": 25, "d1": 61, "r1": 62, "i1": 63, "p2": 25, "d2": 5, "r2": 6, "i2": 63, "p3": 25, "d3": 5, "r3": 6, "i3": 63, "o1": 64, "o2": 65, "o3": 7, "o4": 7}, "IA": {"s": 66, "p1": 9, "d1": 67, "r1": 68, "i1": 68, "p2": 9, "d2": 5, "r2": 6, "i2": 68, "p3": 9, "d3": 5, "r3": 6, "i3": 68, "o1": 69, "o2": 70, "o3": 7, "o4": 7}, "ID": {"s": 71, "p1": 9, "d1": 72, "r1": 73, "i1": 74, "p2": 9, "d2": 5, "r2": 6, "i2": 74, "p3": 9, "d3": 5, "r3": 6, "i3": 74, "o1": 75, "o2": 76, "o3": 7, "o4": 7}, "IL": {"s": 77, "p1": 9, "d1": 78, "r1": 79, "i1": 79, "p2": 9, "d2": 5, "r2": 6, "i2": 79, "p3": 9, "d3": 5, "r3": 6, "i3": 79, "o1": 80, "o2": 81, "o3": 82, "o4": 7}, "IN": {"s": 83, "p4": 9, "d4": 5, "r4": 84, "i4": 84, "p5": 9, "d5": 85, "r5": 44, "i5": 84, "p6": 9, "d6": 86, "r6": 44, "i6": 84, "p7": 9, "d7": 87, "r7": 44, "i7": 84, "p8": 9, "d8": 88, "r8": 44, "i8": 84, "o1": 7, "o2": 7, "o3": 7, "o4": 7}, "KS": {"s": 89, "p1": 9, "d1": 90, "r1": 91, "i1": 92, "p2": 9, "d2": 5, "r2": 6, "i2": 92, "p3": 9, "d3": 5, "r3": 6, "i3": 92, "o1": 93, "o2": 94, "o3": 95, "o4": 7}, "KY": {"s": 96, "p4": 9, "d4": 97, "r4": 98, "i4": 98, "p5": 9, "d5": 5, "r5": 44, "i5": 98, "p6": 9, "d6": 5, "r6": 44, "i6": 98, "p7": 9, "d7": 5, "r7": 44, "i7": 98, "p8": 9, "d8": 5, "r8": 44, "i8": 98, "o1": 7, "o2": 7, "o3": 7, "o4": 7}, "LA": {"s": 99, "p4": 25, "d4": 100, "r4": 101, "i4": 100, "p5": 25, "d5": 5, "r5": 102, "i5": 100, "p6": 25, "d6": 5, "r6": 103, "i6": 100, "p7": 25, "d7": 5, "r7": 104, "i7": 100, "p8": 25, "d8": 5, "r8": 105, "i8": 100, "o1": 7, "o2": 7, "o3": 7, "o4": 7}, "MA": {"s": 106, "p1": 9, "d1": 107, "r1": 108, "i1": 108, "p2": 9, "d2": 5, "r2": 6, "i2": 108, "p3": 9, "d3": 5, "r3": 6, "i3": 108, "o1": 7, "o2": 7, "o3": 7, "o4": 7}, "MD": {"s": 109, "p1": 9, "d1": 110, "r1": 111, "i1": 111, "p2": 9, "d2": 5, "r2": 6, "i2": 111, "p3": 9, "d3": 5, "r3": 6, "i3": 111, "o1": 112, "o2": 113, "o3": 7, "o4": 7}, "ME": {"s": 114, "p1": 9, "d1": 115, "r1": 116, "i1": 117, "p2": 9, "d2": 5, "r2": 6, "i2": 117, "p3": 9, "d3": 5, "r3": 6, "i3": 117, "o1": 118, "o2": 119, "o3": 120, "o4": 7}, "MI": {"s": 121, "p1": 9, "d1": 122, "r1": 123, "i1": 124, "p2": 9, "d2": 5, "r2": 6, "i2": 124, "p3": 9, "d3": 5, "r3": 6, "i3": 124, "o1": 125, "o2": 126, "o3": 127, "o4": 7}, "MN": {"s": 128, "p1": 25, "d1": 129, "r1": 130, "i1": 131, "p2": 25, "d2": 5, "r2": 6, "i2": 131, "p3": 25, "d3": 5, "r3": 6, "i3": 131, "o1": 132, "o2": 133, "o3": 7, "o4": 7}, "MO": {"s": 134, "p4": 9, "d4": 5, "r4": 135, "i4": 135, "p5": 9, "d5": 136, "r5": 44, "i5": 135, "p6": 9, "d6": 137, "r6": 44, "i6": 135, "p7": 9, "d7": 138, "r7": 44, "i7": 135, "p8": 9, "d8": 139, "r8": 44, "i8": 135, "o1": 7, "o2": 7, "o3": 7, "o4": 7}, "MS": {"s": 140, "p4": 9, "d4": 141, "r4": 44, "i4": 142, "p5": 9, "d5": 5, "r5": 143, "i5": 142, "p6": 9, "d6": 5, "r6": 144, "i6": 142, "p7": 9, "d7": 5, "r7": 145, "i7": 142, "p8": 9, "d8": 5, "r8": 44, "i8": 142, "o1": 7, "o2": 7, "o3": 7, "o4": 7}, "MT": {"s": 146, "p4": 25, "d4": 5, "r4": 44, "i4": 147, "p5": 25, "d5": 148, "r5": 149, "i5": 147, "p6": 25, "d6": 150, "r6": 151, "i6": 147, "p7": 25, "d7": 152, "r7": 153, "i7": 147, "p8": 25, "d8": 5, "r8": 154, "i8": 147, "o1": 7, "o2": 7, "o3": 7, "o4": 7}, "NC": {"s": 155, "p4": 25, "d4": 156, "r4": 44, "i4": 156, "p5": 25, "d5": 157, "r5": 158, "i5": 156, "p6": 25, "d6": 159, "r6": 160, "i6": 156, "p7": 25, "d7": 161, "r7": 162, "i7": 156, "p8": 25, "d8": 5, "r8": 163, "i8": 156, "o1": 7, "o2": 7, "o3": 7, "o4": 7}, "ND": {"s": 164, "p4": 9, "d4": 5, "r4": 165, "i4": 165, "p5": 9, "d5": 166, "r5": 44, "i5": 165, "p6": 9, "d6": 167, "r6": 44, "i6": 165, "p7": 9, "d7": 168, "r7": 44, "i7": 165, "p8": 9, "d8": 169, "r8": 44, "i8": 165, "o1": 7, "o2": 7, "o3": 7, "o4": 7}, "NE": {"s": 170, "p1": 9, "d1": 171, "r1": 172, "i1": 172, "p2": 9, "d2": 5, "r2": 6, "i2": 172, "p3": 9, "d3": 5, "r3": 6, "i3": 172, "o1": 7, "o2": 7, "o3": 7, "o4": 7}, "NH": {"s": 173, "p4": 9, "d4": 174, "r4": 175, "i4": 175, "p5": 9, "d5": 5, "r5": 44, "i5": 175, "p6": 9, "d6": 5, "r6": 44, "i6": 175, "p7": 9, "d7": 5, "r7": 44, "i7": 175, "p8": 9, "d8": 5, "r8": 44, "i8": 175, "o1": 176, "o2": 7, "o3": 7, "o4": 7}, "NM": {"s": 177, "p1": 9, "d1": 178, "r1": 179, "i1": 180, "p2": 9, "d2": 5, "r2": 6, "i2": 180, "p3": 9, "d3": 5, "r3": 6, "i3": 180, "o1": 7, "o2": 7, "o3": 7, "o4": 7}, "NV": {"s": 181, "p1": 9, "d1": 182, "r1": 183, "i1": 184, "p2": 9, "d2": 5, "r2": 6, "i2": 184, "p3": 9, "d3": 5, "r3": 6, "i3": 184, "o1": 185, "o2": 186, "o3": 187, "o4": 7}, "NY": {"s": 188, "p1": 25, "d1": 189, "r1": 190, "i1": 189, "p2": 25, "d2": 5, "r2": 6, "i2": 189, "p3": 25, "d3": 5, "r3": 6, "i3": 189, "o1": 191, "o2": 192, "o3": 193, "o4": 7}, "OH": {"s": 194, "p1": 9, "d1": 195, "r1": 196, "i1": 197, "p2": 9, "d2": 5, "r2": 6, "i2": 197, "p3": 9, "d3": 5, "r3": 6, "i3": 197, "o1": 198, "o2": 199, "o3": 7, "o4": 7}, "OK": {"s": 200, "p1": 9, "d1": 201, "r1": 202, "i1": 203, "p2": 9, "d2": 5, "r2": 6, "i2": 203, "p3": 9, "d3": 5, "r3": 6, "i3": 203, "o1": 204, "o2": 7, "o3": 7, "o4": 7}, "OR": {"s": 205, "p1": 25, "d1": 206, "r1": 207, "i1": 206, "p2": 25, "d2": 5, "r2": 6, "i2": 206, "p3": 25, "d3": 5, "r3": 6, "i3": 206, "o1": 7, "o2": 7, "o3": 7, "o4": 7}, "PA": {"s": 208, "p1": 25, "d1": 209, "r1": 210, "i1": 209, "p2": 25, "d2": 5, "r2": 6, "i2": 209, "p3": 25, "d3": 5, "r3": 6, "i3": 209, "o1": 211, "o2": 212, "o3": 7, "o4": 7}, "RI": {"s": 213, "p1": 25, "d1": 214, "r1": 215, "i1": 214, "p2": 25, "d2": 5, "r2": 6, "i2": 214, "p3": 25, "d3": 5, "r3": 6, "i3": 214, "o1": 216, "o2": 217, "o3": 218, "o4": 7}, "SC": {"s": 219, "p1": 9, "d1": 220, "r1": 221, "i1": 221, "p2": 9, "d2": 5, "r2": 6, "i2": 221, "p3": 9, "d3": 5, "r3": 6, "i3": 221, "o1": 222, "o2": 223, "o3": 7, "o4": 7}, "SD": {"s": 224, "p1": 9, "d1": 225, "r1": 226, "i1": 227, "p2": 9, "d2": 5, "r2": 6, "i2": 227, "p3": 9, "d3": 5, "r3": 6, "i3": 227, "o1": 228, "o2": 7, "o3": 7, "o4": 7}, "TN": {"s": 229, "p1": 9, "d1": 230, "r1": 231, "i1": 232, "p2": 9, "d2": 5, "r2": 6, "i2": 232, "p3": 9, "d3": 5, "r3": 6, "i3": 232, "o1": 233, "o2": 234, "o3": 235, "o4": 7}, "TX": {"s": 236, "p1": 9, "d1": 237, "r1": 238, "i1": 238, "p2": 9, "d2": 5, "r2": 6, "i2": 238, "p3": 9, "d3": 5, "r3": 6, "i3": 238, "o1": 239, "o2": 240, "o3": 7, "o4": 7}, "UT": {"s": 241, "p4": 9, "d4": 5, "r4": 44, "i4": 242, "p5": 9, "d5": 243, "r5": 244, "i5": 242, "p6": 9, "d6": 245, "r6": 246, "i6": 242, "p7": 9, "d7": 247, "r7": 248, "i7": 242, "p8": 9, "d8": 5, "r8": 249, "i8": 242, "o1": 7, "o2": 7, "o3": 7, "o4": 7}, "VT": {"s": 250, "p4": 9, "d4": 251, "r4": 252, "i4": 252, "p5": 9, "d5": 5, "r5": 44, "i5": 252, "p6": 9, "d6": 5, "r6": 44, "i6": 252, "p7": 9, "d7": 5, "r7": 44, "i7": 252, "p8": 9, "d8": 5, "r8": 44, "i8": 252, "o1": 253, "o2": 254, "o3": 7, "o4": 7}, "WA": {"s": 255, "p4": 25, "d4": 256, "r4": 44, "i4": 256, "p5": 25, "d5": 257, "r5": 258, "i5": 256, "p6": 25, "d6": 259, "r6": 260, "i6": 256, "p7": 25, "d7": 261, "r7": 262, "i7": 256, "p8": 25, "d8": 5, "r8": 263, "i8": 256, "o1": 7, "o2": 7, "o3": 7, "o4": 7}, "WI": {"s": 264, "p1": 9, "d1": 265, "r1": 266, "i1": 266, "p2": 9, "d2": 5, "r2": 6, "i2": 266, "p3": 9, "d3": 5, "r3": 6, "i3": 266, "o1": 267, "o2": 268, "o3": 269, "o4": 7}, "WV": {"s": 270, "p4": 9, "d4": 5, "r4": 271, "i4": 271, "p5": 9, "d5": 272, "r5": 273, "i5": 271, "p6": 9, "d6": 274, "r6": 275, "i6": 271, "p7": 9, "d7": 276, "r7": 277, "i7": 271, "p8": 9, "d8": 278, "r8": 44, "i8": 271, "o1": 7, "o2": 7, "o3": 7, "o4": 7}, "WY": {"s": 279, "p1": 9, "d1": 280, "r1": 281, "i1": 282, "p2": 9, "d2": 5, "r2": 6, "i2": 282, "p3": 9, "d3": 5, "r3": 6, "i3": 282, "o1": 7, "o2": 7, "o3": 7, "o4": 7}}, "values": {"0": "AK", "1": "I", "2": "Democrat Mark Begich", "3": "Republican Mike Dunleavy", "4": "Independent Bill Walker", "5": "A Democratic Candidate", "6": "Republican _none_", "7": "_none_", "8": "AL", "9": "R", "10": "Democrat Walt Maddox", "11": "Republican Kay Ivey", "12": "Independent Chad Chig Martin", "13": "Independent Chris Countryman", "14": "Independent Tony Hewitt Jr", "15": "AR", "16": "Democrat Jared Henderson", "17": "Republican Asa Hutchinson", "18": "Libertarian Mark West", "19": "AZ", "20": "Democrat David Garcia", "21": "Republican Doug Ducey", "22": "Green Party candidate Angel Torres", "23": "Libertarian Kevin McCormick", "24": "CA", "25": "D", "26": "Democrat Gavin Newsom", "27": "Republican John Cox", "28": "Democrat Jerry Brown", "29": "CO", "30": "Democrat Jared Polis", "31": "Republican Walker Stapleton", "32": "Democrat John Hickenlooper", "33": "Unity Party Candidate Bill Hammons", "34": "Libertarian Scott Helker", "35": "CT", "36": "Democrat Ned Lamont", "37": "Republican Bob Stefanowski", "38": "Democrat Dannel Malloy", "39": "Libertarian  Rod Hanscomb", "40": "Amigo Constitution Party candidate Mark Stewart Greenstein", "41": "Independent Oz Griebel", "42": "DE", "43": "Democrat John Carney", "44": "A Republican Candidate", "45": "Republican Ken Simpler", "46": "Republican Chuck Boyce", "47": "Republican         \nGerald Hocker", "48": "FL", "49": "Democrat Andrew Gillum", "50": "Republican Ron DeSantis", "51": "Republican Rick Scott", "52": "Reform Party candidate Darcy Richardson", "53": "Independent Ryan Foley", "54": "Independent Kyle Gibson", "55": "GA", "56": "Democrat Stacey Abrams", "57": "Republican Brian Kemp", "58": "Republican Nathan Deal", "59": "Libertarian Ted Metz", "60": "HI", "61": "Democrat Colleen Hanabusa", "62": "Republican Andria Tupola", "63": "Democrat David Ige", "64": "Green Party candidate Jim Brewer", "65": "Independent Terrence Teruya", "66": "IA", "67": "Democrat Fred Hubbell", "68": "Republican Kim Reynolds", "69": "Libertarian Jake Porter", "70": "Clear Water Party of Iowa candidate Gary Siegwarth", "71": "ID", "72": "Democrat Paulette Jordan", "73": "Republican Brad Little", "74": "Republican Butch Otter", "75": "Constitution Party candidate Walter Bayes", "76": "Libertarian Bev Boeck", "77": "IL", "78": "Democrat J.B. Pritzker", "79": "Republican Bruce Rauner", "80": "Constitution Party candidate William Kelly", "81": "Libertarian Kash Jackson", "82": "Conservative Party Candidate Sam McCann", "83": "IN", "84": "Republican Eric Holcomb", "85": "Democrat Evan Bayh", "86": "Democrat Pete Buttigieg", "87": "Democrat Joe Donnelly", "88": "Democrat John Gregg", "89": "KS", "90": "Democrat Laura Kelly", "91": "Republican Kris Kobach", "92": "Republican Jeff Colyer", "93": "Independent Greg Orman", "94": "Libertarian Jeff Caldwel", "95": "Independent Rick Kloos", "96": "KY", "97": "Democrat Andy Beshear", "98": "Republican Matt Bevin", "99": "LA", "100": "Democrat John Bel Edwards", "101": "Republican Ralph Abraham", "102": "Republican Eddie Rispone", "103": "Republican John Fleming", "104": "Republican Charles Boustany", "105": "Republican Eric Skrmetta", "106": "MA", "107": "Democrat Jay Gonzalez", "108": "Republican Charlie Baker", "109": "MD", "110": "Democrat Ben Jealous", "111": "Republican Larry Hogan", "112": "Green Party candidate Ian Schlakman", "113": "Libertarian Shawn Quinn", "114": "ME", "115": "Democrat Janet Mills", "116": "Republican Derek Levasseu", "117": "Republican Paul LePage", "118": "Independent Teresea Hayes", "119": "Independent Alan Caron", "120": "Green Party candidate Jay Parker Dresser", "121": "MI", "122": "Democrat Gretchen Whitmer", "123": "Republican Bill Schuette", "124": "Republican Rick Snyder", "125": "Libertarian Bill Gelinau", "126": "Green Party candidate Jennifer Kurland", "127": "Natural Law Party candidate Keith Butkovich", "128": "MN", "129": "Democrat Tim Walz", "130": "Republican Jeff Johnson", "131": "Democrat Mark Dayton", "132": "Libertarian Josh Welter", "133": "Grassroots Party Candidate Chris Wright", "134": "MO", "135": "Republican Mike Parson", "136": "Democrat Nicole Galloway", "137": "Democrat Jason Kander", "138": "Democrat Sly James", "139": "Democrat Stephen Webber", "140": "MS", "141": "Democrat Jim Hood", "142": "Republican Phil Bryant", "143": "Republican Tate Reeves", "144": "Republican Robert Foster", "145": "Republican Bill Waller", "146": "MT", "147": "Democrat Steve Bullock", "148": "Democrat Casey Schreiner", "149": "Republican Tim Fox", "150": "Democrat Reilly Neill", "151": "Republican Greg Gianforte", "152": "Democrat Mike Cooney", "153": "Republican Matt Rosendale", "154": "Republican Corey Stapleton", "155": "NC", "156": "Democrat Roy Cooper", "157": "Democrat Josh Stein", "158": "Republican Dan Forest", "159": "Democrat Anthony Foxx", "160": "Republican Pat McCrory", "161": "Democrat Jeff Jackson", "162": "Republican Walter Jones Jr.", "163": "Republican Cherie Berry", "164": "ND", "165": "Republican Doug Burgum", "166": "Democrat Heidi Heitkamp", "167": "Democrat Joshua Boschee", "168": "Democrat Joan Heckaman", "169": "Democrat Kent Conrad", "170": "NE", "171": "Democrat Bob Krist", "172": "Republican Pete Ricketts", "173": "NH", "174": "Democrat Molly Kelly", "175": "Republican Chris Sununu", "176": "Libertarian Jilletta Jarvis", "177": "NM", "178": "Democrat Michelle Lujan Grisham", "179": "Republican Steve Pearce", "180": "Republican Susana Martinez", "181": "NV", "182": "Democrat Steve Sisolak", "183": "Republican Adam Laxalt", "184": "Republican Brian Sandoval", "185": "Independent American party candidate Russell Best", "186": "Libertarian Jared Lord", "187": "None of the above", "188": "NY", "189": "Democrat Andrew Cuomo", "190": "Republican Marc Molinaro", "191": "Libertarian Larry Sharpe", "192": "Green Party candidate Howie Hawkins", "193": "Independent Stephanie Miner", "194": "OH", "195": "Democrat Richard Cordray", "196": "Republican Mike DeWine", "197": "Republican John Kasich", "198": "Green Party candidate Constance Gadell Newton", "199": "Libertarian Travis Irvine", "200": "OK", "201": "Democrat Drew Edmondson", "202": "Republican Kevin Stitt", "203": "Republican Mary Fallin", "204": "Libertarian Chris Powell", "205": "OR", "206": "Democrat Kate Brown", "207": "Republican Knute Buehler", "208": "PA", "209": "Democrat Tom Wolf", "210": "Republican Scott Wagner", "211": "Libertarian Ken Krawchuk", "212": "Green Party candidate Paul Glover", "213": "RI", "214": "Democrat Gina Raimondo", "215": "Republican Allan Fung", "216": "Moderate Party candidate Bill Gilbert", "217": "Independent Joseph Trillo", "218": "Compassion Party candidate Anne Armstrong", "219": "SC", "220": "Democrat James Smith", "221": "Republican Henry McMaster", "222": "American Party candidate Martin Barry", "223": "Independent Phil Cheney", "224": "SD", "225": "Democrat Billie Sutton", "226": "Republican Kristi Noem", "227": "Republican Dennis Daugaard", "228": "Independent Lora Hubbel", "229": "TN", "230": "Democrat Karl Dean", "231": "Republican Bill Lee", "232": "Republican Bill Haslam", "233": "Independent Gabriel Fancher", "234": "Independent Joe Wilmoth", "235": "Independent Rick Tyler", "236": "TX", "237": "Democrat Lupe Valdez", "238": "Republican Greg Abbott", "239": "Libertarian Mark Tippetts", "240": "Green Party candidate Janis Richards", "241": "UT", "242": "Republican Gary Herbert", "243": "Democrat Jim Matheson", "244": "Republican Rob Bishop", "245": "Democrat Gene Davis", "246": "Republican Jason Chaffetz", "247": "Democrat Brian King", "248": "Republican Spencer Cox", "249": "Republican Sean Reyes", "250": "VT", "251": "Democrat Christine Hallquist", "252": "Republican Phil Scott", "253": "Independent Joseph Barney", "254": "Earth Rights Party candidate Stephen Marx", "255": "WA", "256": "Democrat Jay Inslee", "257": "Democrat Dow Constantine", "258": "Republican Bill Bryant", "259": "Democrat Bob Ferguson", "260": "Republican Drew C. MacEwen", "261": "Democrat Pramila Jayapal", "262": "Republican Dave Reichert", "263": "Republican Dino Rossi", "264": "WI", "265": "Democrat Tony Evers", "266": "Republican Scott Walker", "267": "Libertarian Phillip Anderson", "268": "Green Party candidate Michael White", "269": "Wisconsin Party candidate Arnie Enz", "270": "WV", "271": "Republican Jim Justice", "272": "Democrat Booth Goodwin", "273": "Republican Roger Hanshaw", "274": "Democrat Natalie Tennant", "275": "Republican David McKinley", "276": "Democrat Woody Thrasher", "277": "Republican Mac Warner", "278": "Democrat Joe Manchin", "279": "WY", "280": "Democrat Mary Throne", "281": "Republican Mark Gordon", "282": "Republican Matt Mead"}, "geos": {"AK": "AK", "AL": "AL", "AR": "AR", "AZ": "AZ", "CA": "CA", "CO": "CO", "CT": "CT", "DE": "DE", "FL": "FL", "GA": "GA", "HI": "HI", "IA": "IA", "ID": "ID", "IL": "IL", "IN": "IN", "KS": "KS", "KY": "KY", "LA": "LA", "MA": "MA", "MD": "MD", "ME": "ME", "MI": "MI", "MN": "MN", "MO": "MO", "MS": "MS", "MT": "MT", "NC": "NC", "ND": "ND", "NE": "NE", "NH": "NH", "NM": "NM", "NV": "NV", "NY": "NY", "OH": "OH", "OK": "OK", "OR": "OR", "PA": "PA", "RI": "RI", "SC": "SC", "SD": "SD", "TN": "TN", "TX": "TX", "UT": "UT", "VT": "VT", "WA": "WA", "WI": "WI", "WV": "WV", "WY": "WY"}, "rand": 563412782}