{"top": {"Democrat Beto O'Rourke": "TX", "Democrat Elizabeth Warren": "MA", "Democrat Bernie Sanders": "VT", "Democrat Joe Biden": "DE", "Democrat Kamala Harris": "CA", "Democrat Cory Booker": "NJ"}, "bottom": {"Democrat John Delaney": "MD", "Democrat Pete Buttigieg": "IN", "Democrat Steve Bullock": "MT", "Democrat Andrew Yang": "NY", "Democrat Julian Castro": "TX", "Democrat Michael Bennet": "CO", "Democrat Amy Klobuchar": "MN", "Democrat Marianne Williamson": "CA", "Democrat Tom Steyer": "CA", "Democrat Tulsi Gabbard": "HI"}, "fav": {"Democrat Michael Sadowsky": "test", "Democrat Sarah Graham": "test"}, "rand": 0.4728}