{"Democrat Stacey Abrams": {"min": 0, "max": 26113, "rand": 0.3}, "Democrat Michael Bennet": {"min": 26114, "max": 59792, "rand": 0.76}, "Democrat Beto O'Rourke": {"min": 59793, "max": 108376, "rand": 0.09}, "Democrat Joe Biden": {"min": 108377, "max": 251311, "rand": 0.93}, "Democrat Cory Booker": {"min": 251312, "max": 310038, "rand": 0.07}, "Democrat Steve Bullock": {"min": 310039, "max": 346520, "rand": 0.21}, "Democrat Pete Buttigieg": {"min": 346521, "max": 427169, "rand": 0.15}, "Democrat Julian Castro": {"min": 427170, "max": 456810, "rand": 0.82}, "Democrat Bill de Blasio": {"min": 456811, "max": 476142, "rand": 0.41}, "Democrat John Delaney": {"min": 476143, "max": 512263, "rand": 0.59}, "Democrat Tulsi Gabbard": {"min": 512264, "max": 541904, "rand": 0.33}, "Democrat Kirsten Gillibrand": {"min": 541905, "max": 568017, "rand": 0.02}, "Democrat Kamala Harris": {"min": 568018, "max": 642759, "rand": 0.16}, "Democrat Jay Inslee": {"min": 642760, "max": 662091, "rand": 0.38}, "Democrat Amy Klobuchar": {"min": 662092, "max": 698842, "rand": 0.85}, "Democrat Seth Moulton": {"min": 698843, "max": 718174, "rand": 0.65}, "Democrat Tim Ryan": {"min": 718175, "max": 750360, "rand": 0.65}, "Democrat Bernie Sanders": {"min": 750361, "max": 853358, "rand": 0.06}, "Democrat Tom Steyer": {"min": 853359, "max": 872690, "rand": 0.02}, "Democrat Elizabeth Warren": {"min": 872691, "max": 935150, "rand": 0.49}, "Democrat Marianne Williamson": {"min": 935151, "max": 954482, "rand": 0.75}, "Democrat Andrew Yang": {"min": 954483, "max": 1000000, "rand": 0.38}}