{"districts": {"AK": {"s": 0, "p1": 1, "d1": 2, "r1": 2, "i1": 2, "p8": 3, "d8": 4, "r8": 5, "i8": 6, "p9": 3, "d9": 7, "r9": 5, "i9": 6, "p10": 3, "d10": 7, "r10": 5, "i10": 6, "p11": 3, "d11": 7, "r11": 5, "i11": 6, "p12": 3, "d12": 7, "r12": 5, "i12": 6, "p13": 3, "d13": 7, "r13": 5, "i13": 6, "p14": 3, "d14": 7, "r14": 5, "i14": 6, "p3": 1, "d3": 2, "r3": 2, "i3": 2, "p4": 1, "d4": 2, "r4": 2, "i4": 2, "p5": 1, "d5": 2, "r5": 2, "i5": 2, "p6": 1, "d6": 2, "r6": 2, "i6": 2, "p7": 3, "d7": 7, "r7": 8, "i7": 8, "o1": 2, "o2": 2, "o3": 2, "o4": 2}, "AL": {"s": 9, "p1": 1, "d1": 2, "r1": 2, "i1": 2, "p8": 10, "d8": 11, "r8": 12, "i8": 13, "p9": 10, "d9": 7, "r9": 14, "i9": 13, "p10": 10, "d10": 7, "r10": 15, "i10": 13, "p11": 10, "d11": 7, "r11": 16, "i11": 13, "p12": 10, "d12": 7, "r12": 17, "i12": 13, "p13": 10, "d13": 7, "r13": 5, "i13": 13, "p14": 10, "d14": 7, "r14": 5, "i14": 13, "p3": 1, "d3": 2, "r3": 2, "i3": 2, "p4": 1, "d4": 2, "r4": 2, "i4": 2, "p5": 1, "d5": 2, "r5": 2, "i5": 2, "p6": 1, "d6": 2, "r6": 2, "i6": 2, "p7": 10, "d7": 18, "r7": 5, "i7": 18, "o1": 2, "o2": 2, "o3": 2, "o4": 2}, "AR": {"s": 19, "p1": 1, "d1": 2, "r1": 2, "i1": 2, "p8": 3, "d8": 20, "r8": 5, "i8": 6, "p9": 3, "d9": 21, "r9": 5, "i9": 6, "p10": 3, "d10": 7, "r10": 5, "i10": 6, "p11": 3, "d11": 7, "r11": 5, "i11": 6, "p12": 3, "d12": 7, "r12": 5, "i12": 6, "p13": 3, "d13": 7, "r13": 5, "i13": 6, "p14": 3, "d14": 7, "r14": 5, "i14": 6, "p3": 1, "d3": 2, "r3": 2, "i3": 2, "p4": 1, "d4": 2, "r4": 2, "i4": 2, "p5": 1, "d5": 2, "r5": 2, "i5": 2, "p6": 1, "d6": 2, "r6": 2, "i6": 2, "p7": 3, "d7": 7, "r7": 22, "i7": 22, "o1": 2, "o2": 2, "o3": 2, "o4": 2}, "AZ": {"s": 23, "p1": 3, "d1": 24, "r1": 25, "i1": 26, "p8": 3, "d8": 27, "r8": 5, "i8": 6, "p9": 3, "d9": 28, "r9": 5, "i9": 6, "p10": 3, "d10": 7, "r10": 5, "i10": 6, "p11": 3, "d11": 7, "r11": 5, "i11": 6, "p12": 3, "d12": 7, "r12": 5, "i12": 6, "p13": 3, "d13": 7, "r13": 5, "i13": 6, "p14": 3, "d14": 7, "r14": 5, "i14": 6, "p3": 3, "d3": 7, "r3": 5, "i3": 6, "p4": 3, "d4": 7, "r4": 5, "i4": 6, "p5": 3, "d5": 7, "r5": 5, "i5": 6, "p6": 3, "d6": 7, "r6": 5, "i6": 6, "p7": 3, "d7": 7, "r7": 25, "i7": 25, "o1": 29, "o2": 30, "o3": 2, "o4": 2}, "CA": {"s": 31, "p1": 10, "d1": 32, "r1": 33, "i1": 32, "p3": 10, "d3": 7, "r3": 5, "i3": 13, "p4": 10, "d4": 7, "r4": 5, "i4": 13, "p5": 10, "d5": 7, "r5": 5, "i5": 13, "p6": 10, "d6": 7, "r6": 5, "i6": 13, "o1": 2, "o2": 2, "o3": 2, "o4": 2}, "CO": {"s": 34, "p1": 1, "d1": 2, "r1": 2, "i1": 2, "p8": 3, "d8": 35, "r8": 36, "i8": 6, "p9": 3, "d9": 37, "r9": 5, "i9": 6, "p10": 3, "d10": 38, "r10": 5, "i10": 6, "p11": 3, "d11": 39, "r11": 5, "i11": 6, "p12": 3, "d12": 40, "r12": 5, "i12": 6, "p13": 3, "d13": 7, "r13": 5, "i13": 6, "p14": 3, "d14": 7, "r14": 5, "i14": 6, "p3": 1, "d3": 2, "r3": 2, "i3": 2, "p4": 1, "d4": 2, "r4": 2, "i4": 2, "p5": 1, "d5": 2, "r5": 2, "i5": 2, "p6": 1, "d6": 2, "r6": 2, "i6": 2, "p7": 3, "d7": 7, "r7": 41, "i7": 41, "o1": 2, "o2": 2, "o3": 2, "o4": 2}, "CT": {"s": 42, "p1": 10, "d1": 43, "r1": 44, "i1": 43, "p3": 10, "d3": 7, "r3": 5, "i3": 13, "p4": 10, "d4": 7, "r4": 5, "i4": 13, "p5": 10, "d5": 7, "r5": 5, "i5": 13, "p6": 10, "d6": 7, "r6": 5, "i6": 13, "o1": 2, "o2": 2, "o3": 2, "o4": 2}, "DE": {"s": 45, "p1": 10, "d1": 46, "r1": 47, "i1": 46, "p8": 10, "d8": 48, "r8": 49, "i8": 13, "p9": 10, "d9": 7, "r9": 5, "i9": 13, "p10": 10, "d10": 7, "r10": 5, "i10": 13, "p11": 10, "d11": 7, "r11": 5, "i11": 13, "p12": 10, "d12": 7, "r12": 5, "i12": 13, "p13": 10, "d13": 7, "r13": 5, "i13": 13, "p14": 10, "d14": 7, "r14": 5, "i14": 13, "p3": 10, "d3": 7, "r3": 5, "i3": 13, "p4": 10, "d4": 7, "r4": 5, "i4": 13, "p5": 10, "d5": 7, "r5": 5, "i5": 13, "p6": 10, "d6": 7, "r6": 5, "i6": 13, "p7": 10, "d7": 50, "r7": 5, "i7": 50, "o1": 2, "o2": 2, "o3": 2, "o4": 2}, "FL": {"s": 51, "p1": 10, "d1": 52, "r1": 53, "i1": 52, "p3": 10, "d3": 7, "r3": 5, "i3": 13, "p4": 10, "d4": 7, "r4": 5, "i4": 13, "p5": 10, "d5": 7, "r5": 5, "i5": 13, "p6": 10, "d6": 7, "r6": 5, "i6": 13, "o1": 54, "o2": 2, "o3": 2, "o4": 2}, "GA": {"s": 55, "p1": 1, "d1": 2, "r1": 2, "i1": 2, "p8": 3, "d8": 56, "r8": 57, "i8": 6, "p9": 3, "d9": 58, "r9": 5, "i9": 6, "p10": 3, "d10": 59, "r10": 5, "i10": 6, "p11": 3, "d11": 60, "r11": 5, "i11": 6, "p12": 3, "d12": 61, "r12": 5, "i12": 6, "p13": 3, "d13": 7, "r13": 5, "i13": 6, "p14": 3, "d14": 7, "r14": 5, "i14": 6, "p3": 1, "d3": 2, "r3": 2, "i3": 2, "p4": 1, "d4": 2, "r4": 2, "i4": 2, "p5": 1, "d5": 2, "r5": 2, "i5": 2, "p6": 1, "d6": 2, "r6": 2, "i6": 2, "p7": 3, "d7": 7, "r7": 62, "i7": 62, "o1": 2, "o2": 2, "o3": 2, "o4": 2}, "HI": {"s": 63, "p1": 10, "d1": 64, "r1": 65, "i1": 64, "p3": 10, "d3": 7, "r3": 5, "i3": 13, "p4": 10, "d4": 7, "r4": 5, "i4": 13, "p5": 10, "d5": 7, "r5": 5, "i5": 13, "p6": 10, "d6": 7, "r6": 5, "i6": 13, "o1": 66, "o2": 2, "o3": 2, "o4": 2}, "IA": {"s": 67, "p1": 1, "d1": 2, "r1": 2, "i1": 2, "p8": 3, "d8": 68, "r8": 69, "i8": 6, "p9": 3, "d9": 70, "r9": 5, "i9": 6, "p10": 3, "d10": 71, "r10": 5, "i10": 6, "p11": 3, "d11": 72, "r11": 5, "i11": 6, "p12": 3, "d12": 73, "r12": 5, "i12": 6, "p13": 3, "d13": 7, "r13": 5, "i13": 6, "p14": 3, "d14": 7, "r14": 5, "i14": 6, "p3": 1, "d3": 2, "r3": 2, "i3": 2, "p4": 1, "d4": 2, "r4": 2, "i4": 2, "p5": 1, "d5": 2, "r5": 2, "i5": 2, "p6": 1, "d6": 2, "r6": 2, "i6": 2, "p7": 3, "d7": 7, "r7": 74, "i7": 74, "o1": 2, "o2": 2, "o3": 2, "o4": 2}, "ID": {"s": 75, "p1": 1, "d1": 2, "r1": 2, "i1": 2, "p8": 3, "d8": 7, "r8": 76, "i8": 6, "p9": 3, "d9": 7, "r9": 5, "i9": 6, "p10": 3, "d10": 7, "r10": 5, "i10": 6, "p11": 3, "d11": 7, "r11": 5, "i11": 6, "p12": 3, "d12": 7, "r12": 5, "i12": 6, "p13": 3, "d13": 7, "r13": 5, "i13": 6, "p14": 3, "d14": 7, "r14": 5, "i14": 6, "p3": 1, "d3": 2, "r3": 2, "i3": 2, "p4": 1, "d4": 2, "r4": 2, "i4": 2, "p5": 1, "d5": 2, "r5": 2, "i5": 2, "p6": 1, "d6": 2, "r6": 2, "i6": 2, "p7": 3, "d7": 7, "r7": 77, "i7": 77, "o1": 2, "o2": 2, "o3": 2, "o4": 2}, "IL": {"s": 78, "p1": 1, "d1": 2, "r1": 2, "i1": 2, "p8": 10, "d8": 79, "r8": 80, "i8": 13, "p9": 10, "d9": 7, "r9": 81, "i9": 13, "p10": 10, "d10": 7, "r10": 82, "i10": 13, "p11": 10, "d11": 7, "r11": 83, "i11": 13, "p12": 10, "d12": 7, "r12": 5, "i12": 13, "p13": 10, "d13": 7, "r13": 5, "i13": 13, "p14": 10, "d14": 7, "r14": 5, "i14": 13, "p3": 1, "d3": 2, "r3": 2, "i3": 2, "p4": 1, "d4": 2, "r4": 2, "i4": 2, "p5": 1, "d5": 2, "r5": 2, "i5": 2, "p6": 1, "d6": 2, "r6": 2, "i6": 2, "p7": 10, "d7": 84, "r7": 5, "i7": 84, "o1": 2, "o2": 2, "o3": 2, "o4": 2}, "IN": {"s": 85, "p1": 10, "d1": 86, "r1": 87, "i1": 86, "p3": 10, "d3": 7, "r3": 5, "i3": 13, "p4": 10, "d4": 7, "r4": 5, "i4": 13, "p5": 10, "d5": 7, "r5": 5, "i5": 13, "p6": 10, "d6": 7, "r6": 5, "i6": 13, "o1": 88, "o2": 2, "o3": 2, "o4": 2}, "KS": {"s": 89, "p1": 1, "d1": 2, "r1": 2, "i1": 2, "p8": 3, "d8": 90, "r8": 91, "i8": 6, "p9": 3, "d9": 92, "r9": 93, "i9": 6, "p10": 3, "d10": 94, "r10": 95, "i10": 6, "p11": 3, "d11": 96, "r11": 97, "i11": 6, "p12": 3, "d12": 7, "r12": 98, "i12": 6, "p13": 3, "d13": 7, "r13": 5, "i13": 6, "p14": 3, "d14": 7, "r14": 5, "i14": 6, "p3": 1, "d3": 2, "r3": 2, "i3": 2, "p4": 1, "d4": 2, "r4": 2, "i4": 2, "p5": 1, "d5": 2, "r5": 2, "i5": 2, "p6": 1, "d6": 2, "r6": 2, "i6": 2, "p7": 3, "d7": 7, "r7": 5, "i7": 99, "o1": 2, "o2": 2, "o3": 2, "o4": 2}, "KY": {"s": 100, "p1": 1, "d1": 2, "r1": 2, "i1": 2, "p8": 3, "d8": 101, "r8": 102, "i8": 6, "p9": 3, "d9": 103, "r9": 5, "i9": 6, "p10": 3, "d10": 7, "r10": 5, "i10": 6, "p11": 3, "d11": 7, "r11": 5, "i11": 6, "p12": 3, "d12": 7, "r12": 5, "i12": 6, "p13": 3, "d13": 7, "r13": 5, "i13": 6, "p14": 3, "d14": 7, "r14": 5, "i14": 6, "p3": 1, "d3": 2, "r3": 2, "i3": 2, "p4": 1, "d4": 2, "r4": 2, "i4": 2, "p5": 1, "d5": 2, "r5": 2, "i5": 2, "p6": 1, "d6": 2, "r6": 2, "i6": 2, "p7": 3, "d7": 7, "r7": 104, "i7": 104, "o1": 2, "o2": 2, "o3": 2, "o4": 2}, "LA": {"s": 105, "p1": 1, "d1": 2, "r1": 2, "i1": 2, "p8": 3, "d8": 106, "r8": 107, "i8": 6, "p9": 3, "d9": 108, "r9": 5, "i9": 6, "p10": 3, "d10": 109, "r10": 5, "i10": 6, "p11": 3, "d11": 7, "r11": 5, "i11": 6, "p12": 3, "d12": 7, "r12": 5, "i12": 6, "p13": 3, "d13": 7, "r13": 5, "i13": 6, "p14": 3, "d14": 7, "r14": 5, "i14": 6, "p3": 1, "d3": 2, "r3": 2, "i3": 2, "p4": 1, "d4": 2, "r4": 2, "i4": 2, "p5": 1, "d5": 2, "r5": 2, "i5": 2, "p6": 1, "d6": 2, "r6": 2, "i6": 2, "p7": 3, "d7": 7, "r7": 110, "i7": 110, "o1": 2, "o2": 2, "o3": 2, "o4": 2}, "MA": {"s": 111, "p1": 10, "d1": 112, "r1": 113, "i1": 112, "p8": 10, "d8": 114, "r8": 115, "i8": 13, "p9": 10, "d9": 7, "r9": 113, "i9": 13, "p10": 10, "d10": 7, "r10": 5, "i10": 13, "p11": 10, "d11": 7, "r11": 5, "i11": 13, "p12": 10, "d12": 7, "r12": 5, "i12": 13, "p13": 10, "d13": 7, "r13": 5, "i13": 13, "p14": 10, "d14": 7, "r14": 5, "i14": 13, "p3": 10, "d3": 7, "r3": 5, "i3": 13, "p4": 10, "d4": 7, "r4": 5, "i4": 13, "p5": 10, "d5": 7, "r5": 5, "i5": 13, "p6": 10, "d6": 7, "r6": 5, "i6": 13, "p7": 10, "d7": 116, "r7": 5, "i7": 116, "o1": 2, "o2": 117, "o3": 2, "o4": 2}, "MD": {"s": 118, "p1": 10, "d1": 119, "r1": 120, "i1": 119, "p3": 10, "d3": 7, "r3": 5, "i3": 13, "p4": 10, "d4": 7, "r4": 5, "i4": 13, "p5": 10, "d5": 7, "r5": 5, "i5": 13, "p6": 10, "d6": 7, "r6": 5, "i6": 13, "o1": 121, "o2": 2, "o3": 2, "o4": 2}, "ME": {"s": 122, "p1": 123, "d1": 124, "r1": 125, "i1": 124, "p8": 3, "d8": 126, "r8": 127, "i8": 6, "p9": 3, "d9": 128, "r9": 5, "i9": 6, "p10": 3, "d10": 129, "r10": 5, "i10": 6, "p11": 3, "d11": 130, "r11": 5, "i11": 6, "p12": 3, "d12": 131, "r12": 5, "i12": 6, "p13": 3, "d13": 7, "r13": 5, "i13": 6, "p14": 3, "d14": 7, "r14": 5, "i14": 6, "p3": 123, "d3": 7, "r3": 5, "i3": 132, "p4": 123, "d4": 7, "r4": 5, "i4": 132, "p5": 123, "d5": 7, "r5": 5, "i5": 132, "p6": 123, "d6": 7, "r6": 5, "i6": 132, "p7": 3, "d7": 7, "r7": 133, "i7": 133, "o1": 134, "o2": 135, "o3": 136, "o4": 2}, "MI": {"s": 137, "p1": 10, "d1": 138, "r1": 139, "i1": 138, "p8": 10, "d8": 140, "r8": 139, "i8": 13, "p9": 10, "d9": 7, "r9": 5, "i9": 13, "p10": 10, "d10": 7, "r10": 5, "i10": 13, "p11": 10, "d11": 7, "r11": 5, "i11": 13, "p12": 10, "d12": 7, "r12": 5, "i12": 13, "p13": 10, "d13": 7, "r13": 5, "i13": 13, "p14": 10, "d14": 7, "r14": 5, "i14": 13, "p3": 10, "d3": 7, "r3": 5, "i3": 13, "p4": 10, "d4": 7, "r4": 5, "i4": 13, "p5": 10, "d5": 7, "r5": 5, "i5": 13, "p6": 10, "d6": 7, "r6": 5, "i6": 13, "p7": 10, "d7": 141, "r7": 5, "i7": 141, "o1": 142, "o2": 2, "o3": 2, "o4": 2}, "MN": {"s": 143, "p1": 10, "d1": 144, "r1": 145, "i1": 144, "p8": 10, "d8": 146, "r8": 147, "i8": 13, "p9": 10, "d9": 7, "r9": 148, "i9": 13, "p10": 10, "d10": 7, "r10": 149, "i10": 13, "p11": 10, "d11": 7, "r11": 5, "i11": 13, "p12": 10, "d12": 7, "r12": 5, "i12": 13, "p13": 10, "d13": 7, "r13": 5, "i13": 13, "p14": 10, "d14": 7, "r14": 5, "i14": 13, "p2": 150, "d2": 151, "r2": 149, "i2": 2, "p3": 10, "d3": 7, "r3": 5, "i3": 13, "p4": 10, "d4": 7, "r4": 5, "i4": 13, "p5": 10, "d5": 7, "r5": 5, "i5": 13, "p6": 10, "d6": 7, "r6": 5, "i6": 13, "p7": 10, "d7": 151, "r7": 5, "i7": 151, "o1": 152, "o2": 2, "o3": 2, "o4": 153}, "MO": {"s": 154, "p1": 10, "d1": 155, "r1": 156, "i1": 155, "p3": 10, "d3": 7, "r3": 5, "i3": 13, "p4": 10, "d4": 7, "r4": 5, "i4": 13, "p5": 10, "d5": 7, "r5": 5, "i5": 13, "p6": 10, "d6": 7, "r6": 5, "i6": 13, "o1": 157, "o2": 158, "o3": 159, "o4": 2}, "MS": {"s": 160, "p1": 3, "d1": 161, "r1": 162, "i1": 162, "p8": 3, "d8": 163, "r8": 164, "i8": 6, "p9": 3, "d9": 165, "r9": 5, "i9": 6, "p10": 3, "d10": 7, "r10": 5, "i10": 6, "p11": 3, "d11": 7, "r11": 5, "i11": 6, "p12": 3, "d12": 7, "r12": 5, "i12": 6, "p13": 3, "d13": 7, "r13": 5, "i13": 6, "p14": 3, "d14": 7, "r14": 5, "i14": 6, "p2": 150, "d2": 165, "r2": 166, "i2": 2, "p3": 3, "d3": 7, "r3": 5, "i3": 6, "p4": 3, "d4": 7, "r4": 5, "i4": 6, "p5": 3, "d5": 7, "r5": 5, "i5": 6, "p6": 3, "d6": 7, "r6": 5, "i6": 6, "p7": 3, "d7": 7, "r7": 166, "i7": 166, "o1": 167, "o2": 168, "o3": 2, "o4": 2}, "MT": {"s": 169, "p1": 10, "d1": 170, "r1": 171, "i1": 170, "p8": 3, "d8": 172, "r8": 173, "i8": 6, "p9": 3, "d9": 174, "r9": 5, "i9": 6, "p10": 3, "d10": 7, "r10": 5, "i10": 6, "p11": 3, "d11": 7, "r11": 5, "i11": 6, "p12": 3, "d12": 7, "r12": 5, "i12": 6, "p13": 3, "d13": 7, "r13": 5, "i13": 6, "p14": 3, "d14": 7, "r14": 5, "i14": 6, "p3": 10, "d3": 7, "r3": 5, "i3": 13, "p4": 10, "d4": 7, "r4": 5, "i4": 13, "p5": 10, "d5": 7, "r5": 5, "i5": 13, "p6": 10, "d6": 7, "r6": 5, "i6": 13, "p7": 3, "d7": 7, "r7": 175, "i7": 175, "o1": 2, "o2": 176, "o3": 2, "o4": 2}, "NC": {"s": 177, "p1": 1, "d1": 2, "r1": 2, "i1": 2, "p8": 3, "d8": 178, "r8": 179, "i8": 6, "p9": 3, "d9": 180, "r9": 5, "i9": 6, "p10": 3, "d10": 181, "r10": 5, "i10": 6, "p11": 3, "d11": 7, "r11": 5, "i11": 6, "p12": 3, "d12": 7, "r12": 5, "i12": 6, "p13": 3, "d13": 7, "r13": 5, "i13": 6, "p14": 3, "d14": 7, "r14": 5, "i14": 6, "p3": 1, "d3": 2, "r3": 2, "i3": 2, "p4": 1, "d4": 2, "r4": 2, "i4": 2, "p5": 1, "d5": 2, "r5": 2, "i5": 2, "p6": 1, "d6": 2, "r6": 2, "i6": 2, "p7": 3, "d7": 7, "r7": 182, "i7": 182, "o1": 2, "o2": 2, "o3": 2, "o4": 2}, "ND": {"s": 183, "p1": 10, "d1": 184, "r1": 185, "i1": 184, "p3": 10, "d3": 7, "r3": 5, "i3": 13, "p4": 10, "d4": 7, "r4": 5, "i4": 13, "p5": 10, "d5": 7, "r5": 5, "i5": 13, "p6": 10, "d6": 7, "r6": 5, "i6": 13, "o1": 2, "o2": 2, "o3": 2, "o4": 2}, "NE": {"s": 186, "p1": 3, "d1": 187, "r1": 188, "i1": 188, "p8": 3, "d8": 189, "r8": 190, "i8": 6, "p9": 3, "d9": 191, "r9": 5, "i9": 6, "p10": 3, "d10": 7, "r10": 5, "i10": 6, "p11": 3, "d11": 7, "r11": 5, "i11": 6, "p12": 3, "d12": 7, "r12": 5, "i12": 6, "p13": 3, "d13": 7, "r13": 5, "i13": 6, "p14": 3, "d14": 7, "r14": 5, "i14": 6, "p3": 3, "d3": 7, "r3": 5, "i3": 6, "p4": 3, "d4": 7, "r4": 5, "i4": 6, "p5": 3, "d5": 7, "r5": 5, "i5": 6, "p6": 3, "d6": 7, "r6": 5, "i6": 6, "p7": 3, "d7": 7, "r7": 192, "i7": 192, "o1": 2, "o2": 2, "o3": 2, "o4": 2}, "NH": {"s": 193, "p1": 1, "d1": 2, "r1": 2, "i1": 2, "p8": 10, "d8": 194, "r8": 195, "i8": 13, "p9": 10, "d9": 7, "r9": 196, "i9": 13, "p10": 10, "d10": 7, "r10": 197, "i10": 13, "p11": 10, "d11": 7, "r11": 198, "i11": 13, "p12": 10, "d12": 7, "r12": 5, "i12": 13, "p13": 10, "d13": 7, "r13": 5, "i13": 13, "p14": 10, "d14": 7, "r14": 5, "i14": 13, "p3": 1, "d3": 2, "r3": 2, "i3": 2, "p4": 1, "d4": 2, "r4": 2, "i4": 2, "p5": 1, "d5": 2, "r5": 2, "i5": 2, "p6": 1, "d6": 2, "r6": 2, "i6": 2, "p7": 10, "d7": 199, "r7": 5, "i7": 199, "o1": 2, "o2": 2, "o3": 2, "o4": 2}, "NJ": {"s": 200, "p1": 10, "d1": 201, "r1": 202, "i1": 201, "p8": 10, "d8": 203, "r8": 204, "i8": 13, "p9": 10, "d9": 7, "r9": 5, "i9": 13, "p10": 10, "d10": 7, "r10": 5, "i10": 13, "p11": 10, "d11": 7, "r11": 5, "i11": 13, "p12": 10, "d12": 7, "r12": 5, "i12": 13, "p13": 10, "d13": 7, "r13": 5, "i13": 13, "p14": 10, "d14": 7, "r14": 5, "i14": 13, "p3": 10, "d3": 7, "r3": 5, "i3": 13, "p4": 10, "d4": 7, "r4": 5, "i4": 13, "p5": 10, "d5": 7, "r5": 5, "i5": 13, "p6": 10, "d6": 7, "r6": 5, "i6": 13, "p7": 10, "d7": 205, "r7": 5, "i7": 205, "o1": 206, "o2": 207, "o3": 208, "o4": 2}, "NM": {"s": 209, "p1": 10, "d1": 210, "r1": 211, "i1": 210, "p8": 10, "d8": 212, "r8": 5, "i8": 13, "p9": 10, "d9": 7, "r9": 5, "i9": 13, "p10": 10, "d10": 7, "r10": 5, "i10": 13, "p11": 10, "d11": 7, "r11": 5, "i11": 13, "p12": 10, "d12": 7, "r12": 5, "i12": 13, "p13": 10, "d13": 7, "r13": 5, "i13": 13, "p14": 10, "d14": 7, "r14": 5, "i14": 13, "p3": 10, "d3": 7, "r3": 5, "i3": 13, "p4": 10, "d4": 7, "r4": 5, "i4": 13, "p5": 10, "d5": 7, "r5": 5, "i5": 13, "p6": 10, "d6": 7, "r6": 5, "i6": 13, "p7": 10, "d7": 7, "r7": 5, "i7": 213, "o1": 214, "o2": 2, "o3": 2, "o4": 2}, "NV": {"s": 215, "p1": 3, "d1": 216, "r1": 217, "i1": 217, "p3": 3, "d3": 7, "r3": 5, "i3": 6, "p4": 3, "d4": 7, "r4": 5, "i4": 6, "p5": 3, "d5": 7, "r5": 5, "i5": 6, "p6": 3, "d6": 7, "r6": 5, "i6": 6, "o1": 218, "o2": 219, "o3": 220, "o4": 2}, "NY": {"s": 221, "p1": 10, "d1": 222, "r1": 223, "i1": 222, "p3": 10, "d3": 7, "r3": 5, "i3": 13, "p4": 10, "d4": 7, "r4": 5, "i4": 13, "p5": 10, "d5": 7, "r5": 5, "i5": 13, "p6": 10, "d6": 7, "r6": 5, "i6": 13, "o1": 2, "o2": 2, "o3": 2, "o4": 2}, "OH": {"s": 224, "p1": 10, "d1": 225, "r1": 226, "i1": 225, "p3": 10, "d3": 7, "r3": 5, "i3": 13, "p4": 10, "d4": 7, "r4": 5, "i4": 13, "p5": 10, "d5": 7, "r5": 5, "i5": 13, "p6": 10, "d6": 7, "r6": 5, "i6": 13, "o1": 227, "o2": 2, "o3": 2, "o4": 2}, "OK": {"s": 228, "p1": 1, "d1": 2, "r1": 2, "i1": 2, "p8": 3, "d8": 229, "r8": 230, "i8": 6, "p9": 3, "d9": 231, "r9": 5, "i9": 6, "p10": 3, "d10": 232, "r10": 5, "i10": 6, "p11": 3, "d11": 7, "r11": 5, "i11": 6, "p12": 3, "d12": 7, "r12": 5, "i12": 6, "p13": 3, "d13": 7, "r13": 5, "i13": 6, "p14": 3, "d14": 7, "r14": 5, "i14": 6, "p3": 1, "d3": 2, "r3": 2, "i3": 2, "p4": 1, "d4": 2, "r4": 2, "i4": 2, "p5": 1, "d5": 2, "r5": 2, "i5": 2, "p6": 1, "d6": 2, "r6": 2, "i6": 2, "p7": 3, "d7": 7, "r7": 233, "i7": 233, "o1": 2, "o2": 2, "o3": 2, "o4": 2}, "OR": {"s": 234, "p1": 1, "d1": 2, "r1": 2, "i1": 2, "p8": 10, "d8": 235, "r8": 5, "i8": 13, "p9": 10, "d9": 7, "r9": 5, "i9": 13, "p10": 10, "d10": 7, "r10": 5, "i10": 13, "p11": 10, "d11": 7, "r11": 5, "i11": 13, "p12": 10, "d12": 7, "r12": 5, "i12": 13, "p13": 10, "d13": 7, "r13": 5, "i13": 13, "p14": 10, "d14": 7, "r14": 5, "i14": 13, "p3": 1, "d3": 2, "r3": 2, "i3": 2, "p4": 1, "d4": 2, "r4": 2, "i4": 2, "p5": 1, "d5": 2, "r5": 2, "i5": 2, "p6": 1, "d6": 2, "r6": 2, "i6": 2, "p7": 10, "d7": 236, "r7": 5, "i7": 236, "o1": 2, "o2": 2, "o3": 2, "o4": 2}, "PA": {"s": 237, "p1": 10, "d1": 238, "r1": 239, "i1": 238, "p3": 10, "d3": 7, "r3": 5, "i3": 13, "p4": 10, "d4": 7, "r4": 5, "i4": 13, "p5": 10, "d5": 7, "r5": 5, "i5": 13, "p6": 10, "d6": 7, "r6": 5, "i6": 13, "o1": 240, "o2": 241, "o3": 2, "o4": 2}, "RI": {"s": 242, "p1": 10, "d1": 243, "r1": 244, "i1": 243, "p8": 10, "d8": 245, "r8": 5, "i8": 13, "p9": 10, "d9": 7, "r9": 5, "i9": 13, "p10": 10, "d10": 7, "r10": 5, "i10": 13, "p11": 10, "d11": 7, "r11": 5, "i11": 13, "p12": 10, "d12": 7, "r12": 5, "i12": 13, "p13": 10, "d13": 7, "r13": 5, "i13": 13, "p14": 10, "d14": 7, "r14": 5, "i14": 13, "p3": 10, "d3": 7, "r3": 5, "i3": 13, "p4": 10, "d4": 7, "r4": 5, "i4": 13, "p5": 10, "d5": 7, "r5": 5, "i5": 13, "p6": 10, "d6": 7, "r6": 5, "i6": 13, "p7": 10, "d7": 246, "r7": 5, "i7": 246, "o1": 2, "o2": 2, "o3": 2, "o4": 2}, "SC": {"s": 247, "p1": 1, "d1": 2, "r1": 2, "i1": 2, "p8": 3, "d8": 248, "r8": 249, "i8": 6, "p9": 3, "d9": 250, "r9": 5, "i9": 6, "p10": 3, "d10": 7, "r10": 5, "i10": 6, "p11": 3, "d11": 7, "r11": 5, "i11": 6, "p12": 3, "d12": 7, "r12": 5, "i12": 6, "p13": 3, "d13": 7, "r13": 5, "i13": 6, "p14": 3, "d14": 7, "r14": 5, "i14": 6, "p3": 1, "d3": 2, "r3": 2, "i3": 2, "p4": 1, "d4": 2, "r4": 2, "i4": 2, "p5": 1, "d5": 2, "r5": 2, "i5": 2, "p6": 1, "d6": 2, "r6": 2, "i6": 2, "p7": 3, "d7": 7, "r7": 251, "i7": 251, "o1": 2, "o2": 2, "o3": 2, "o4": 2}, "SD": {"s": 252, "p1": 1, "d1": 2, "r1": 2, "i1": 2, "p8": 3, "d8": 253, "r8": 254, "i8": 6, "p9": 3, "d9": 255, "r9": 5, "i9": 6, "p10": 3, "d10": 7, "r10": 5, "i10": 6, "p11": 3, "d11": 7, "r11": 5, "i11": 6, "p12": 3, "d12": 7, "r12": 5, "i12": 6, "p13": 3, "d13": 7, "r13": 5, "i13": 6, "p14": 3, "d14": 7, "r14": 5, "i14": 6, "p3": 1, "d3": 2, "r3": 2, "i3": 2, "p4": 1, "d4": 2, "r4": 2, "i4": 2, "p5": 1, "d5": 2, "r5": 2, "i5": 2, "p6": 1, "d6": 2, "r6": 2, "i6": 2, "p7": 3, "d7": 7, "r7": 256, "i7": 256, "o1": 2, "o2": 2, "o3": 2, "o4": 2}, "TN": {"s": 257, "p1": 3, "d1": 258, "r1": 259, "i1": 260, "p8": 3, "d8": 261, "r8": 262, "i8": 6, "p9": 3, "d9": 263, "r9": 264, "i9": 6, "p10": 3, "d10": 265, "r10": 266, "i10": 6, "p11": 3, "d11": 7, "r11": 267, "i11": 6, "p12": 3, "d12": 7, "r12": 268, "i12": 6, "p13": 3, "d13": 7, "r13": 5, "i13": 6, "p14": 3, "d14": 7, "r14": 5, "i14": 6, "p3": 3, "d3": 7, "r3": 5, "i3": 6, "p4": 3, "d4": 7, "r4": 5, "i4": 6, "p5": 3, "d5": 7, "r5": 5, "i5": 6, "p6": 3, "d6": 7, "r6": 5, "i6": 6, "p7": 3, "d7": 7, "r7": 5, "i7": 269, "o1": 270, "o2": 271, "o3": 272, "o4": 2}, "TX": {"s": 273, "p1": 3, "d1": 274, "r1": 275, "i1": 275, "p8": 3, "d8": 274, "r8": 276, "i8": 6, "p9": 3, "d9": 277, "r9": 5, "i9": 6, "p10": 3, "d10": 278, "r10": 5, "i10": 6, "p11": 3, "d11": 279, "r11": 5, "i11": 6, "p12": 3, "d12": 280, "r12": 5, "i12": 6, "p13": 3, "d13": 7, "r13": 5, "i13": 6, "p14": 3, "d14": 7, "r14": 5, "i14": 6, "p3": 3, "d3": 7, "r3": 5, "i3": 6, "p4": 3, "d4": 7, "r4": 5, "i4": 6, "p5": 3, "d5": 7, "r5": 5, "i5": 6, "p6": 3, "d6": 7, "r6": 5, "i6": 6, "p7": 3, "d7": 7, "r7": 281, "i7": 281, "o1": 282, "o2": 2, "o3": 2, "o4": 2}, "UT": {"s": 283, "p1": 3, "d1": 284, "r1": 285, "i1": 286, "p3": 3, "d3": 7, "r3": 5, "i3": 6, "p4": 3, "d4": 7, "r4": 5, "i4": 6, "p5": 3, "d5": 7, "r5": 5, "i5": 6, "p6": 3, "d6": 7, "r6": 5, "i6": 6, "o1": 287, "o2": 2, "o3": 2, "o4": 2}, "VA": {"s": 288, "p1": 10, "d1": 289, "r1": 290, "i1": 289, "p8": 10, "d8": 291, "r8": 5, "i8": 13, "p9": 10, "d9": 7, "r9": 5, "i9": 13, "p10": 10, "d10": 7, "r10": 5, "i10": 13, "p11": 10, "d11": 7, "r11": 5, "i11": 13, "p12": 10, "d12": 7, "r12": 5, "i12": 13, "p13": 10, "d13": 7, "r13": 5, "i13": 13, "p14": 10, "d14": 7, "r14": 5, "i14": 13, "p3": 10, "d3": 7, "r3": 5, "i3": 13, "p4": 10, "d4": 7, "r4": 5, "i4": 13, "p5": 10, "d5": 7, "r5": 5, "i5": 13, "p6": 10, "d6": 7, "r6": 5, "i6": 13, "p7": 10, "d7": 292, "r7": 5, "i7": 292, "o1": 293, "o2": 2, "o3": 2, "o4": 2}, "VT": {"s": 294, "p1": 123, "d1": 295, "r1": 296, "i1": 297, "p3": 123, "d3": 7, "r3": 5, "i3": 132, "p4": 123, "d4": 7, "r4": 5, "i4": 132, "p5": 123, "d5": 7, "r5": 5, "i5": 132, "p6": 123, "d6": 7, "r6": 5, "i6": 132, "o1": 2, "o2": 2, "o3": 2, "o4": 2}, "WA": {"s": 298, "p1": 10, "d1": 299, "r1": 300, "i1": 299, "p3": 10, "d3": 7, "r3": 5, "i3": 13, "p4": 10, "d4": 7, "r4": 5, "i4": 13, "p5": 10, "d5": 7, "r5": 5, "i5": 13, "p6": 10, "d6": 7, "r6": 5, "i6": 13, "o1": 2, "o2": 2, "o3": 2, "o4": 2}, "WI": {"s": 301, "p1": 10, "d1": 302, "r1": 303, "i1": 302, "p3": 10, "d3": 7, "r3": 5, "i3": 13, "p4": 10, "d4": 7, "r4": 5, "i4": 13, "p5": 10, "d5": 7, "r5": 5, "i5": 13, "p6": 10, "d6": 7, "r6": 5, "i6": 13, "o1": 2, "o2": 2, "o3": 2, "o4": 2}, "WV": {"s": 304, "p1": 10, "d1": 305, "r1": 306, "i1": 305, "p8": 3, "d8": 307, "r8": 308, "i8": 6, "p9": 3, "d9": 309, "r9": 5, "i9": 6, "p10": 3, "d10": 7, "r10": 5, "i10": 6, "p11": 3, "d11": 7, "r11": 5, "i11": 6, "p12": 3, "d12": 7, "r12": 5, "i12": 6, "p13": 3, "d13": 7, "r13": 5, "i13": 6, "p14": 3, "d14": 7, "r14": 5, "i14": 6, "p3": 10, "d3": 7, "r3": 5, "i3": 13, "p4": 10, "d4": 7, "r4": 5, "i4": 13, "p5": 10, "d5": 7, "r5": 5, "i5": 13, "p6": 10, "d6": 7, "r6": 5, "i6": 13, "p7": 3, "d7": 7, "r7": 310, "i7": 310, "o1": 2, "o2": 2, "o3": 2, "o4": 2}, "WY": {"s": 311, "p1": 3, "d1": 312, "r1": 313, "i1": 313, "p8": 3, "d8": 7, "r8": 314, "i8": 6, "p9": 3, "d9": 7, "r9": 5, "i9": 6, "p10": 3, "d10": 7, "r10": 5, "i10": 6, "p11": 3, "d11": 7, "r11": 5, "i11": 6, "p12": 3, "d12": 7, "r12": 5, "i12": 6, "p13": 3, "d13": 7, "r13": 5, "i13": 6, "p14": 3, "d14": 7, "r14": 5, "i14": 6, "p3": 3, "d3": 7, "r3": 5, "i3": 6, "p4": 3, "d4": 7, "r4": 5, "i4": 6, "p5": 3, "d5": 7, "r5": 5, "i5": 6, "p6": 3, "d6": 7, "r6": 5, "i6": 6, "p7": 3, "d7": 7, "r7": 315, "i7": 315, "o1": 316, "o2": 2, "o3": 2, "o4": 2}}, "values": {"0": "AK", "1": " V", "2": "_none_", "3": "R", "4": "Democrat Alyse Galvin", "5": "A Republican Candidate", "6": "Republican _none_", "7": "A Democratic Candidate", "8": "Republican Dan Sullivan", "9": "AL", "10": "D", "11": "Democrat Walt Maddox", "12": "Republican  Jim Zeigler", "13": "Democrat _none_", "14": "Republican Roy Moore", "15": "Republican Will Ainsworth", "16": "Republican Bradley Byrne", "17": "Republican Steve Marshall", "18": "Democrat Doug Jones", "19": "AR", "20": "Democrat Jared Henderson", "21": "Democrat Eddie Armstrong", "22": "Republican Tom Cotton", "23": "AZ", "24": "Democrat Kyrsten Sinema", "25": "Republican Martha McSally", "26": "Republican Jeff Flake", "27": "Democrat Mark Kelly", "28": "Democrat Greg Stanton", "29": "Libertarian Doug Marks", "30": "Green Party candidate Angela Green", "31": "CA", "32": "Democrat Dianne Feinstein", "33": "Democrat Kevin de Le\u00f3n", "34": "CO", "35": "Democrat Joe Neguse", "36": "Republican Walker Stapleton", "37": "Democrat Jason Crow", "38": "Democrat Mike Johnston", "39": "Democrat Andrew Romanof", "40": "Democrat John Hickenlooper", "41": "Republican Cory Gardner", "42": "CT", "43": "Democrat Chris Murphy", "44": "Republican Matthew Corey", "45": "DE", "46": "Democrat Tom Carper", "47": "Republican Gene Truono", "48": "Democrat Lisa Rochester", "49": "Republican Chuck Boyce", "50": "Democrat Chris Coons", "51": "FL", "52": "Democrat Bill Nelson", "53": "Republican Rick Scott", "54": "Libertarian Joe Wendt", "55": "GA", "56": "Democrat Michelle Nunn", "57": "Republican Casey Cagle", "58": "Democrat Teresa Tomlinson", "59": "Democrat Scott Holcomb", "60": "Democrat Sarah Riggs Amico", "61": "Democrat Raphael Warnock", "62": "Republican David Perdue", "63": "HI", "64": "Democrat Mazie Hirono", "65": "Republican Thomas White", "66": "Independent Arturo Reyes", "67": "IA", "68": "Democrat Tom Vilsak", "69": "Republican Paul Pate", "70": "Democrat Cindy Axne", "71": "Democrat Abby Finkenauer", "72": "Democrat Rob Sand", "73": "Democrat Liz Mathis", "74": "Republican Joni Ernst", "75": "ID", "76": "Republican Mike Simpson", "77": "Republican Jim Risch", "78": "IL", "79": "Democrat Evelyn Sanguinetti", "80": "Republican Mike Bost", "81": "Republican Omeed Memar", "82": "Republican Erika Harold", "83": "Republican Rodney Davis", "84": "Democrat Dick Durbin", "85": "IN", "86": "Democrat Joe Donnelly", "87": "Republican Mike Braun", "88": "Libertarian Lucy Brenton", "89": "KS", "90": "Democrat Kathleen Sebelius", "91": "Republican Jeff Colyer", "92": "Democrat Paul Davis", "93": "Republican Kris Kobach", "94": "Democrat Barry Grissom", "95": "Republican Roger Marshall", "96": "Democrat Sharice Davids", "97": "Republican Matt Schlapp", "98": "Republican Mike Pompeop", "99": "Republican Pat Roberts", "100": "KY", "101": "Democrat Matt Jones", "102": "Republican Allison Ball", "103": "Democrat Amy McGrath", "104": "Republican Mitch McConnell", "105": "LA", "106": "Democrat Mitch Landrieu", "107": "Republican John Schroder", "108": "Democrat Foster Campbell", "109": "Democrat Cedric Richmond", "110": "Republican Bill Cassidy", "111": "MA", "112": "Democrat Elizabeth Warren", "113": "Republican Geoff Diehl", "114": "Democrat Seth Moulton", "115": "Republican Karyn Polito", "116": "Democrat Ed Markey", "117": "Independent Shiva Ayyadurai", "118": "MD", "119": "Democrat Ben Cardin", "120": "Republican Tony Campbell", "121": "Libertarian Arvin Vohra", "122": "ME", "123": "I", "124": "Independent Angus King", "125": "Republican Eric Brakey", "126": "Democrat Sara Gideon", "127": "Republican Derek Levasseur", "128": "Democrat Susan Rice", "129": "Democrat Hannah Pingree", "130": "Democrat Adam Cote", "131": "Democrat Jared Golden", "132": "Independent _none_", "133": "Republican Susan Collins", "134": "Democrat Zak Ringelstein", "135": "Independent Benjamin Pollard", "136": "Libertarian Chris Lyons", "137": "MI", "138": "Democrat Debbie Stabenow", "139": "Republican John James", "140": "Democrat Abdul El-Sayed", "141": "Democrat Gary Peters", "142": "Independent Marcia Squier", "143": "MN", "144": "Democrat Amy Klobuchar", "145": "Republican Jim Newberger", "146": "Democrat Peggy Flanagan", "147": "Republican Donna Bergstrom", "148": "Republican Michele Bachmann", "149": "Republican Karin Housley", "150": "none", "151": "Democrat Tina Smith", "152": "Green Party candidate Paula Overby", "153": "Legal Marijuana Now Party candidate Sarah Wellington", "154": "MO", "155": "Democrat Claire McCaskill", "156": "Republican Josh Hawley", "157": "Green Party candidate Jerome Bauer", "158": "Libertarian Japheth Campbell", "159": "Independent Craig O'Dear", "160": "MS", "161": "Democrat David Baria", "162": "Republican Roger Wicker", "163": "Democrat Jim Hood", "164": "Republican Delbert Hosemann", "165": "Democrat Mike Espy", "166": "Republican Cindy Hyde-Smith", "167": "Libertarian Danny Bedwell", "168": "Reform party candidate Shawn O'Hara", "169": "MT", "170": "Democrat Jon Tester", "171": "Republican Matt Rosendale", "172": "Democrat Steve Bullock", "173": "Republican Corey Stapleton", "174": "Democrat Kathleen Williams", "175": "Republican Steve Daines", "176": "Libertarian Rick Breckenridge", "177": "NC", "178": "Democrat Josh Stein", "179": "Republican Mark Walker", "180": "Democrat Anthony Foxx", "181": "Democrat Jeff Jackson", "182": "Republican Thom Tillis", "183": "ND", "184": "Democrat Heidi Heitkamp", "185": "Republican Kevin Cramer", "186": "NE", "187": "Democrat Jane Raybould", "188": "Republican Deb Fischer", "189": "Democrat Chris Beutler", "190": "Republican Mike Foley", "191": "Democrat Sara Howard", "192": "Republican Ben Sasse", "193": "NH", "194": "Democrat Ann McLane Kuster", "195": "Republican Kelly Ayotte", "196": "Republican Jay Lucas", "197": "Republican Scott Brown", "198": "Republican Al Baldasaro", "199": "Democrat Jeanne Shaheen", "200": "NJ", "201": "Democrat Bob Menendez", "202": "Republican Bob Hugin", "203": "Democrat Sheila Oliver", "204": "Republican Matt Rooney", "205": "Democrat Cory Booker", "206": "Libertarian Murray Sabrin", "207": "Green Party candidate Madelyn Hoffman", "208": "Economic Growth Party candidate Hank Schroeder", "209": "NM", "210": "Democrat Martin Heinrich", "211": "Republican Mick Rich", "212": "Democrat Howie Morales", "213": "Democrat Tom Udall", "214": "Libertarian Gary Johnson", "215": "NV", "216": "Democrat Jacky Rosen", "217": "Republican Dean Heller", "218": "Libertarian Tim Hagan", "219": "Independent American Party candidate Kamau Bakari", "220": "None of the above", "221": "NY", "222": "Democrat Kirsten Gillibrand", "223": "Republican David Webber", "224": "OH", "225": "Democrat Sherrod Brown", "226": "Republican Jim Renacci", "227": "Green Party candidate Philena Farley", "228": "OK", "229": "Democrat Brad Henry", "230": "Republican Matt Pinnell", "231": "Democrat Kendra Horn", "232": "Democrat Mike Workma", "233": "Republican Jim Inhofe", "234": "OR", "235": "Democrat Ellen Rosenblum", "236": "Democrat Jeff Merkley", "237": "PA", "238": "Democrat Bob Casey, Jr.", "239": "Republican Lou Barletta", "240": "Libertarian Dale Kerns", "241": "Green Party candidate Neal Gale", "242": "RI", "243": "Democrat Sheldon Whitehouse", "244": "Republican Robert Flanders", "245": "Democrat David Cicilline", "246": "Democrat Jack Reed", "247": "SC", "248": "Democrat Jaime Harrison", "249": "Republican Pamela Evette", "250": "Democrat Mal Hyman", "251": "Republican Lindsey Graham", "252": "SD", "253": "Democrat Billie Sutton", "254": "Republican Dusty Johnson", "255": "Democrat Brendan Johnson", "256": "Republican Mike Rounds", "257": "TN", "258": "Democrat Phil Bredesen", "259": "Republican Marsha Blackburn", "260": "Republican Bob Corker", "261": "Democrat James Mackler", "262": "Republican Bill Haslam", "263": "Democrat Andy Berke", "264": "Republican Mark Green", "265": "Democrat Sara Kyle", "266": "Republican Manny Sethi", "267": "Republican David Kustoff", "268": "Republican Bill Hagerty", "269": "Republican Lamar Alexander", "270": "Independent Trudy Austin", "271": "Independent John Carico", "272": "Independent Dean Hill", "273": "TX", "274": "Democrat Beto O'Rourke", "275": "Republican Ted Cruz", "276": "Republican Dan Patrick", "277": "Democrat Joaquin Castro", "278": "Democrat Mary Hegar", "279": "Democrat Wendy Davis", "280": "Democrat William McRaven", "281": "Republican John Cornyn", "282": "Libertarian Neal Dikeman", "283": "UT", "284": "Democrat Jenny Wilson", "285": "Republican Mitt Romney", "286": "Republican Orrin Hatch", "287": "Libertarian Craig Bowden", "288": "VA", "289": "Democrat Tim Kaine", "290": "Republican Corey Stewart", "291": "Democrat Tom Perriello", "292": "Democrat Mark Warner", "293": "Libertarian Matt Waters", "294": "VT", "295": "Democrat Bernie Sanders", "296": "Republican Brooke Paige", "297": "Independent Bernie Sanders", "298": "WA", "299": "Democrat Maria Cantwell", "300": "Republican Susan Hutchhison", "301": "WI", "302": "Democrat Tammy Baldwin", "303": "Republican Leah Vukmir", "304": "WV", "305": "Democrat Joe Manchin", "306": "Republican Patrick Morrisey", "307": "Democrat Paula Swearengin", "308": "Republican Mitch Carmichael", "309": "Democrat Richard Ojeda", "310": "Republican Shelley Moore Capito", "311": "WY", "312": "Democrat Gary Trauner", "313": "Republican John Barrasso", "314": "Republican Liz Cheney", "315": "Republican Mike Enzi", "316": "Independent David Dodson"}, "geos": {"AK": "AK", "AL": "AL", "AR": "AR", "AZ": "AZ", "CA": "CA", "CO": "CO", "CT": "CT", "DE": "DE", "FL": "FL", "GA": "GA", "HI": "HI", "IA": "IA", "ID": "ID", "IL": "IL", "IN": "IN", "KS": "KS", "KY": "KY", "LA": "LA", "MA": "MA", "MD": "MD", "ME": "ME", "MI": "MI", "MN": "MN", "MO": "MO", "MS": "MS", "MT": "MT", "NC": "NC", "ND": "ND", "NE": "NE", "NH": "NH", "NJ": "NJ", "NM": "NM", "NV": "NV", "NY": "NY", "OH": "OH", "OK": "OK", "OR": "OR", "PA": "PA", "RI": "RI", "SC": "SC", "SD": "SD", "TN": "TN", "TX": "TX", "UT": "UT", "VA": "VA", "VT": "VT", "WA": "WA", "WI": "WI", "WV": "WV", "WY": "WY"}, "rand": 907789577}