{"districts": {"AK": {"id": 0, "s": 1, "p1": 2, "d1": 3, "r1": 3, "dg1": 1, "rg1": 1, "i1": 3, "p8": 4, "d8": 5, "r8": 6, "dg8": 1, "rg8": 1, "i8": 7, "p9": 4, "d9": 8, "r9": 6, "dg9": 1, "rg9": 1, "i9": 7, "p10": 4, "d10": 8, "r10": 6, "dg10": 1, "rg10": 1, "i10": 7, "p11": 4, "d11": 8, "r11": 6, "dg11": 1, "rg11": 1, "i11": 7, "p12": 4, "d12": 8, "r12": 6, "dg12": 1, "rg12": 1, "i12": 7, "p13": 4, "d13": 8, "r13": 6, "dg13": 1, "rg13": 1, "i13": 7, "p14": 4, "d14": 8, "r14": 6, "dg14": 1, "rg14": 1, "i14": 7, "p3": 2, "d3": 3, "r3": 3, "dg3": 1, "rg3": 1, "i3": 3, "p4": 2, "d4": 3, "r4": 3, "dg4": 1, "rg4": 1, "i4": 3, "p5": 2, "d5": 3, "r5": 3, "dg5": 1, "rg5": 1, "i5": 3, "p6": 2, "d6": 3, "r6": 3, "dg6": 1, "rg6": 1, "i6": 3, "p7": 4, "d7": 8, "r7": 9, "dg7": 1, "rg7": 1, "i7": 9, "o1": 3, "o2": 3, "o3": 3, "o4": 3}, "AL": {"id": 10, "s": 11, "p1": 2, "d1": 3, "r1": 3, "dg1": 1, "rg1": 1, "i1": 3, "p8": 12, "d8": 8, "r8": 13, "dg8": 1, "rg8": 1, "i8": 14, "p9": 12, "d9": 8, "r9": 15, "dg9": 1, "rg9": 1, "i9": 14, "p10": 12, "d10": 8, "r10": 16, "dg10": 1, "rg10": 0, "i10": 14, "p11": 12, "d11": 8, "r11": 17, "dg11": 1, "rg11": 1, "i11": 14, "p12": 12, "d12": 8, "r12": 18, "dg12": 1, "rg12": 1, "i12": 14, "p13": 12, "d13": 8, "r13": 19, "dg13": 1, "rg13": 0, "i13": 14, "p14": 12, "d14": 8, "r14": 6, "dg14": 1, "rg14": 1, "i14": 14, "p3": 2, "d3": 3, "r3": 3, "dg3": 1, "rg3": 1, "i3": 3, "p4": 2, "d4": 3, "r4": 3, "dg4": 1, "rg4": 1, "i4": 3, "p5": 2, "d5": 3, "r5": 3, "dg5": 1, "rg5": 1, "i5": 3, "p6": 2, "d6": 3, "r6": 3, "dg6": 1, "rg6": 1, "i6": 3, "p7": 12, "d7": 20, "r7": 6, "dg7": 1, "rg7": 1, "i7": 20, "o1": 3, "o2": 3, "o3": 3, "o4": 3}, "AR": {"id": 21, "s": 22, "p1": 2, "d1": 3, "r1": 3, "dg1": 1, "rg1": 1, "i1": 3, "p8": 4, "d8": 8, "r8": 6, "dg8": 1, "rg8": 1, "i8": 7, "p9": 4, "d9": 8, "r9": 6, "dg9": 1, "rg9": 1, "i9": 7, "p10": 4, "d10": 8, "r10": 6, "dg10": 1, "rg10": 1, "i10": 7, "p11": 4, "d11": 8, "r11": 6, "dg11": 1, "rg11": 1, "i11": 7, "p12": 4, "d12": 8, "r12": 6, "dg12": 1, "rg12": 1, "i12": 7, "p13": 4, "d13": 8, "r13": 6, "dg13": 1, "rg13": 1, "i13": 7, "p14": 4, "d14": 8, "r14": 6, "dg14": 1, "rg14": 1, "i14": 7, "p3": 2, "d3": 3, "r3": 3, "dg3": 1, "rg3": 1, "i3": 3, "p4": 2, "d4": 3, "r4": 3, "dg4": 1, "rg4": 1, "i4": 3, "p5": 2, "d5": 3, "r5": 3, "dg5": 1, "rg5": 1, "i5": 3, "p6": 2, "d6": 3, "r6": 3, "dg6": 1, "rg6": 1, "i6": 3, "p7": 4, "d7": 8, "r7": 23, "dg7": 1, "rg7": 1, "i7": 23, "o1": 3, "o2": 3, "o3": 3, "o4": 3}, "AZ": {"id": 24, "s": 25, "p1": 4, "d1": 26, "r1": 27, "dg1": 1, "rg1": 1, "i1": 28, "p8": 4, "d8": 29, "r8": 30, "dg8": 1, "rg8": 0, "i8": 7, "p9": 4, "d9": 8, "r9": 6, "dg9": 1, "rg9": 1, "i9": 7, "p10": 4, "d10": 8, "r10": 6, "dg10": 1, "rg10": 1, "i10": 7, "p11": 4, "d11": 8, "r11": 6, "dg11": 1, "rg11": 1, "i11": 7, "p12": 4, "d12": 8, "r12": 6, "dg12": 1, "rg12": 1, "i12": 7, "p13": 4, "d13": 8, "r13": 6, "dg13": 1, "rg13": 1, "i13": 7, "p14": 4, "d14": 8, "r14": 6, "dg14": 1, "rg14": 1, "i14": 7, "p3": 4, "d3": 8, "r3": 6, "dg3": 1, "rg3": 1, "i3": 7, "p4": 4, "d4": 8, "r4": 6, "dg4": 1, "rg4": 1, "i4": 7, "p5": 4, "d5": 8, "r5": 6, "dg5": 1, "rg5": 1, "i5": 7, "p6": 4, "d6": 8, "r6": 6, "dg6": 1, "rg6": 1, "i6": 7, "p7": 4, "d7": 8, "r7": 27, "dg7": 1, "rg7": 1, "i7": 27, "o1": 31, "o2": 32, "o3": 3, "o4": 3}, "CA": {"id": 3, "s": 33, "p1": 12, "d1": 34, "r1": 35, "dg1": 1, "rg1": 1, "i1": 34, "p3": 12, "d3": 8, "r3": 6, "dg3": 1, "rg3": 1, "i3": 14, "p4": 12, "d4": 8, "r4": 6, "dg4": 1, "rg4": 1, "i4": 14, "p5": 12, "d5": 8, "r5": 6, "dg5": 1, "rg5": 1, "i5": 14, "p6": 12, "d6": 8, "r6": 6, "dg6": 1, "rg6": 1, "i6": 14, "o1": 3, "o2": 3, "o3": 3, "o4": 3}, "CO": {"id": 36, "s": 37, "p1": 2, "d1": 3, "r1": 3, "dg1": 1, "rg1": 1, "i1": 3, "p8": 4, "d8": 38, "r8": 6, "dg8": 1, "rg8": 1, "i8": 7, "p9": 4, "d9": 39, "r9": 6, "dg9": 1, "rg9": 1, "i9": 7, "p10": 4, "d10": 40, "r10": 6, "dg10": 0, "rg10": 1, "i10": 7, "p11": 4, "d11": 41, "r11": 6, "dg11": 0, "rg11": 1, "i11": 7, "p12": 4, "d12": 42, "r12": 6, "dg12": 0, "rg12": 1, "i12": 7, "p13": 4, "d13": 8, "r13": 6, "dg13": 1, "rg13": 1, "i13": 7, "p14": 4, "d14": 8, "r14": 6, "dg14": 1, "rg14": 1, "i14": 7, "p3": 2, "d3": 3, "r3": 3, "dg3": 1, "rg3": 1, "i3": 3, "p4": 2, "d4": 3, "r4": 3, "dg4": 1, "rg4": 1, "i4": 3, "p5": 2, "d5": 3, "r5": 3, "dg5": 1, "rg5": 1, "i5": 3, "p6": 2, "d6": 3, "r6": 3, "dg6": 1, "rg6": 1, "i6": 3, "p7": 4, "d7": 8, "r7": 43, "dg7": 1, "rg7": 1, "i7": 43, "o1": 3, "o2": 3, "o3": 3, "o4": 3}, "CT": {"id": 3, "s": 44, "p1": 12, "d1": 45, "r1": 46, "dg1": 1, "rg1": 1, "i1": 45, "p3": 12, "d3": 8, "r3": 6, "dg3": 1, "rg3": 1, "i3": 14, "p4": 12, "d4": 8, "r4": 6, "dg4": 1, "rg4": 1, "i4": 14, "p5": 12, "d5": 8, "r5": 6, "dg5": 1, "rg5": 1, "i5": 14, "p6": 12, "d6": 8, "r6": 6, "dg6": 1, "rg6": 1, "i6": 14, "o1": 3, "o2": 3, "o3": 3, "o4": 3}, "DE": {"id": 47, "s": 48, "p1": 12, "d1": 49, "r1": 50, "dg1": 1, "rg1": 1, "i1": 49, "p8": 12, "d8": 51, "r8": 6, "dg8": 1, "rg8": 1, "i8": 14, "p9": 12, "d9": 8, "r9": 6, "dg9": 1, "rg9": 1, "i9": 14, "p10": 12, "d10": 8, "r10": 6, "dg10": 1, "rg10": 1, "i10": 14, "p11": 12, "d11": 8, "r11": 6, "dg11": 1, "rg11": 1, "i11": 14, "p12": 12, "d12": 8, "r12": 6, "dg12": 1, "rg12": 1, "i12": 14, "p13": 12, "d13": 8, "r13": 6, "dg13": 1, "rg13": 1, "i13": 14, "p14": 12, "d14": 8, "r14": 6, "dg14": 1, "rg14": 1, "i14": 14, "p3": 12, "d3": 8, "r3": 6, "dg3": 1, "rg3": 1, "i3": 14, "p4": 12, "d4": 8, "r4": 6, "dg4": 1, "rg4": 1, "i4": 14, "p5": 12, "d5": 8, "r5": 6, "dg5": 1, "rg5": 1, "i5": 14, "p6": 12, "d6": 8, "r6": 6, "dg6": 1, "rg6": 1, "i6": 14, "p7": 12, "d7": 52, "r7": 6, "dg7": 1, "rg7": 1, "i7": 52, "o1": 3, "o2": 3, "o3": 3, "o4": 3}, "FL": {"id": 3, "s": 53, "p1": 12, "d1": 54, "r1": 55, "dg1": 1, "rg1": 1, "i1": 54, "p3": 12, "d3": 8, "r3": 6, "dg3": 1, "rg3": 1, "i3": 14, "p4": 12, "d4": 8, "r4": 6, "dg4": 1, "rg4": 1, "i4": 14, "p5": 12, "d5": 8, "r5": 6, "dg5": 1, "rg5": 1, "i5": 14, "p6": 12, "d6": 8, "r6": 6, "dg6": 1, "rg6": 1, "i6": 14, "o1": 56, "o2": 3, "o3": 3, "o4": 3}, "GA": {"id": 57, "s": 58, "p1": 2, "d1": 3, "r1": 3, "dg1": 1, "rg1": 1, "i1": 3, "p8": 4, "d8": 59, "r8": 6, "dg8": 1, "rg8": 1, "i8": 7, "p9": 4, "d9": 60, "r9": 6, "dg9": 1, "rg9": 1, "i9": 7, "p10": 4, "d10": 61, "r10": 6, "dg10": 1, "rg10": 1, "i10": 7, "p11": 4, "d11": 62, "r11": 6, "dg11": 0, "rg11": 1, "i11": 7, "p12": 4, "d12": 8, "r12": 6, "dg12": 1, "rg12": 1, "i12": 7, "p13": 4, "d13": 8, "r13": 6, "dg13": 1, "rg13": 1, "i13": 7, "p14": 4, "d14": 8, "r14": 6, "dg14": 1, "rg14": 1, "i14": 7, "p3": 2, "d3": 3, "r3": 3, "dg3": 1, "rg3": 1, "i3": 3, "p4": 2, "d4": 3, "r4": 3, "dg4": 1, "rg4": 1, "i4": 3, "p5": 2, "d5": 3, "r5": 3, "dg5": 1, "rg5": 1, "i5": 3, "p6": 2, "d6": 3, "r6": 3, "dg6": 1, "rg6": 1, "i6": 3, "p7": 4, "d7": 8, "r7": 63, "dg7": 1, "rg7": 1, "i7": 63, "o1": 3, "o2": 3, "o3": 3, "o4": 3}, "HI": {"id": 3, "s": 64, "p1": 12, "d1": 65, "r1": 66, "dg1": 1, "rg1": 1, "i1": 65, "p3": 12, "d3": 8, "r3": 6, "dg3": 1, "rg3": 1, "i3": 14, "p4": 12, "d4": 8, "r4": 6, "dg4": 1, "rg4": 1, "i4": 14, "p5": 12, "d5": 8, "r5": 6, "dg5": 1, "rg5": 1, "i5": 14, "p6": 12, "d6": 8, "r6": 6, "dg6": 1, "rg6": 1, "i6": 14, "o1": 67, "o2": 3, "o3": 3, "o4": 3}, "IA": {"id": 68, "s": 69, "p1": 2, "d1": 3, "r1": 3, "dg1": 1, "rg1": 1, "i1": 3, "p8": 4, "d8": 70, "r8": 6, "dg8": 1, "rg8": 1, "i8": 7, "p9": 4, "d9": 71, "r9": 6, "dg9": 1, "rg9": 1, "i9": 7, "p10": 4, "d10": 72, "r10": 6, "dg10": 1, "rg10": 1, "i10": 7, "p11": 4, "d11": 73, "r11": 6, "dg11": 0, "rg11": 1, "i11": 7, "p12": 4, "d12": 8, "r12": 6, "dg12": 1, "rg12": 1, "i12": 7, "p13": 4, "d13": 8, "r13": 6, "dg13": 1, "rg13": 1, "i13": 7, "p14": 4, "d14": 8, "r14": 6, "dg14": 1, "rg14": 1, "i14": 7, "p3": 2, "d3": 3, "r3": 3, "dg3": 1, "rg3": 1, "i3": 3, "p4": 2, "d4": 3, "r4": 3, "dg4": 1, "rg4": 1, "i4": 3, "p5": 2, "d5": 3, "r5": 3, "dg5": 1, "rg5": 1, "i5": 3, "p6": 2, "d6": 3, "r6": 3, "dg6": 1, "rg6": 1, "i6": 3, "p7": 4, "d7": 8, "r7": 74, "dg7": 1, "rg7": 1, "i7": 74, "o1": 3, "o2": 3, "o3": 3, "o4": 3}, "ID": {"id": 75, "s": 76, "p1": 2, "d1": 3, "r1": 3, "dg1": 1, "rg1": 1, "i1": 3, "p8": 4, "d8": 77, "r8": 6, "dg8": 1, "rg8": 1, "i8": 7, "p9": 4, "d9": 78, "r9": 6, "dg9": 0, "rg9": 1, "i9": 7, "p10": 4, "d10": 79, "r10": 6, "dg10": 0, "rg10": 1, "i10": 7, "p11": 4, "d11": 8, "r11": 6, "dg11": 1, "rg11": 1, "i11": 7, "p12": 4, "d12": 8, "r12": 6, "dg12": 1, "rg12": 1, "i12": 7, "p13": 4, "d13": 8, "r13": 6, "dg13": 1, "rg13": 1, "i13": 7, "p14": 4, "d14": 8, "r14": 6, "dg14": 1, "rg14": 1, "i14": 7, "p3": 2, "d3": 3, "r3": 3, "dg3": 1, "rg3": 1, "i3": 3, "p4": 2, "d4": 3, "r4": 3, "dg4": 1, "rg4": 1, "i4": 3, "p5": 2, "d5": 3, "r5": 3, "dg5": 1, "rg5": 1, "i5": 3, "p6": 2, "d6": 3, "r6": 3, "dg6": 1, "rg6": 1, "i6": 3, "p7": 4, "d7": 8, "r7": 80, "dg7": 1, "rg7": 1, "i7": 80, "o1": 3, "o2": 3, "o3": 3, "o4": 3}, "IL": {"id": 81, "s": 82, "p1": 2, "d1": 3, "r1": 3, "dg1": 1, "rg1": 1, "i1": 3, "p8": 12, "d8": 83, "r8": 84, "dg8": 0, "rg8": 1, "i8": 14, "p9": 12, "d9": 8, "r9": 85, "dg9": 1, "rg9": 0, "i9": 14, "p10": 12, "d10": 8, "r10": 86, "dg10": 1, "rg10": 0, "i10": 14, "p11": 12, "d11": 8, "r11": 87, "dg11": 1, "rg11": 0, "i11": 14, "p12": 12, "d12": 8, "r12": 6, "dg12": 1, "rg12": 1, "i12": 14, "p13": 12, "d13": 8, "r13": 6, "dg13": 1, "rg13": 1, "i13": 14, "p14": 12, "d14": 8, "r14": 6, "dg14": 1, "rg14": 1, "i14": 14, "p3": 2, "d3": 3, "r3": 3, "dg3": 1, "rg3": 1, "i3": 3, "p4": 2, "d4": 3, "r4": 3, "dg4": 1, "rg4": 1, "i4": 3, "p5": 2, "d5": 3, "r5": 3, "dg5": 1, "rg5": 1, "i5": 3, "p6": 2, "d6": 3, "r6": 3, "dg6": 1, "rg6": 1, "i6": 3, "p7": 12, "d7": 88, "r7": 6, "dg7": 1, "rg7": 1, "i7": 88, "o1": 3, "o2": 3, "o3": 3, "o4": 3}, "IN": {"id": 3, "s": 89, "p1": 12, "d1": 90, "r1": 91, "dg1": 1, "rg1": 1, "i1": 90, "p3": 12, "d3": 8, "r3": 6, "dg3": 1, "rg3": 1, "i3": 14, "p4": 12, "d4": 8, "r4": 6, "dg4": 1, "rg4": 1, "i4": 14, "p5": 12, "d5": 8, "r5": 6, "dg5": 1, "rg5": 1, "i5": 14, "p6": 12, "d6": 8, "r6": 6, "dg6": 1, "rg6": 1, "i6": 14, "o1": 92, "o2": 3, "o3": 3, "o4": 3}, "KS": {"id": 93, "s": 94, "p1": 2, "d1": 3, "r1": 3, "dg1": 1, "rg1": 1, "i1": 3, "p8": 4, "d8": 95, "r8": 96, "dg8": 1, "rg8": 1, "i8": 7, "p9": 4, "d9": 97, "r9": 98, "dg9": 1, "rg9": 0, "i9": 7, "p10": 4, "d10": 8, "r10": 99, "dg10": 1, "rg10": 0, "i10": 7, "p11": 4, "d11": 8, "r11": 100, "dg11": 1, "rg11": 1, "i11": 7, "p12": 4, "d12": 8, "r12": 6, "dg12": 1, "rg12": 1, "i12": 7, "p13": 4, "d13": 8, "r13": 6, "dg13": 1, "rg13": 1, "i13": 7, "p14": 4, "d14": 8, "r14": 6, "dg14": 1, "rg14": 1, "i14": 7, "p3": 2, "d3": 3, "r3": 3, "dg3": 1, "rg3": 1, "i3": 3, "p4": 2, "d4": 3, "r4": 3, "dg4": 1, "rg4": 1, "i4": 3, "p5": 2, "d5": 3, "r5": 3, "dg5": 1, "rg5": 1, "i5": 3, "p6": 2, "d6": 3, "r6": 3, "dg6": 1, "rg6": 1, "i6": 3, "p7": 4, "d7": 8, "r7": 6, "dg7": 1, "rg7": 1, "i7": 101, "o1": 3, "o2": 3, "o3": 3, "o4": 3}, "KY": {"id": 102, "s": 103, "p1": 2, "d1": 3, "r1": 3, "dg1": 1, "rg1": 1, "i1": 3, "p8": 4, "d8": 104, "r8": 6, "dg8": 1, "rg8": 1, "i8": 7, "p9": 4, "d9": 8, "r9": 6, "dg9": 1, "rg9": 1, "i9": 7, "p10": 4, "d10": 8, "r10": 6, "dg10": 1, "rg10": 1, "i10": 7, "p11": 4, "d11": 8, "r11": 6, "dg11": 1, "rg11": 1, "i11": 7, "p12": 4, "d12": 8, "r12": 6, "dg12": 1, "rg12": 1, "i12": 7, "p13": 4, "d13": 8, "r13": 6, "dg13": 1, "rg13": 1, "i13": 7, "p14": 4, "d14": 8, "r14": 6, "dg14": 1, "rg14": 1, "i14": 7, "p3": 2, "d3": 3, "r3": 3, "dg3": 1, "rg3": 1, "i3": 3, "p4": 2, "d4": 3, "r4": 3, "dg4": 1, "rg4": 1, "i4": 3, "p5": 2, "d5": 3, "r5": 3, "dg5": 1, "rg5": 1, "i5": 3, "p6": 2, "d6": 3, "r6": 3, "dg6": 1, "rg6": 1, "i6": 3, "p7": 4, "d7": 8, "r7": 105, "dg7": 1, "rg7": 1, "i7": 105, "o1": 3, "o2": 3, "o3": 3, "o4": 3}, "LA": {"id": 106, "s": 107, "p1": 2, "d1": 3, "r1": 3, "dg1": 1, "rg1": 1, "i1": 3, "p8": 4, "d8": 108, "r8": 6, "dg8": 1, "rg8": 1, "i8": 7, "p9": 4, "d9": 8, "r9": 6, "dg9": 1, "rg9": 1, "i9": 7, "p10": 4, "d10": 8, "r10": 6, "dg10": 1, "rg10": 1, "i10": 7, "p11": 4, "d11": 8, "r11": 6, "dg11": 1, "rg11": 1, "i11": 7, "p12": 4, "d12": 8, "r12": 6, "dg12": 1, "rg12": 1, "i12": 7, "p13": 4, "d13": 8, "r13": 6, "dg13": 1, "rg13": 1, "i13": 7, "p14": 4, "d14": 8, "r14": 6, "dg14": 1, "rg14": 1, "i14": 7, "p3": 2, "d3": 3, "r3": 3, "dg3": 1, "rg3": 1, "i3": 3, "p4": 2, "d4": 3, "r4": 3, "dg4": 1, "rg4": 1, "i4": 3, "p5": 2, "d5": 3, "r5": 3, "dg5": 1, "rg5": 1, "i5": 3, "p6": 2, "d6": 3, "r6": 3, "dg6": 1, "rg6": 1, "i6": 3, "p7": 4, "d7": 8, "r7": 109, "dg7": 1, "rg7": 1, "i7": 109, "o1": 3, "o2": 3, "o3": 3, "o4": 3}, "MA": {"id": 110, "s": 111, "p1": 12, "d1": 112, "r1": 113, "dg1": 1, "rg1": 1, "i1": 112, "p8": 12, "d8": 114, "r8": 115, "dg8": 1, "rg8": 1, "i8": 14, "p9": 12, "d9": 116, "r9": 6, "dg9": 0, "rg9": 1, "i9": 14, "p10": 12, "d10": 117, "r10": 6, "dg10": 0, "rg10": 1, "i10": 14, "p11": 12, "d11": 8, "r11": 6, "dg11": 1, "rg11": 1, "i11": 14, "p12": 12, "d12": 8, "r12": 6, "dg12": 1, "rg12": 1, "i12": 14, "p13": 12, "d13": 8, "r13": 6, "dg13": 1, "rg13": 1, "i13": 14, "p14": 12, "d14": 8, "r14": 6, "dg14": 1, "rg14": 1, "i14": 14, "p3": 12, "d3": 8, "r3": 6, "dg3": 1, "rg3": 1, "i3": 14, "p4": 12, "d4": 8, "r4": 6, "dg4": 1, "rg4": 1, "i4": 14, "p5": 12, "d5": 8, "r5": 6, "dg5": 1, "rg5": 1, "i5": 14, "p6": 12, "d6": 8, "r6": 6, "dg6": 1, "rg6": 1, "i6": 14, "p7": 12, "d7": 118, "r7": 6, "dg7": 1, "rg7": 1, "i7": 118, "o1": 3, "o2": 119, "o3": 3, "o4": 3}, "MD": {"id": 3, "s": 120, "p1": 12, "d1": 121, "r1": 122, "dg1": 1, "rg1": 1, "i1": 121, "p3": 12, "d3": 8, "r3": 6, "dg3": 1, "rg3": 1, "i3": 14, "p4": 12, "d4": 8, "r4": 6, "dg4": 1, "rg4": 1, "i4": 14, "p5": 12, "d5": 8, "r5": 6, "dg5": 1, "rg5": 1, "i5": 14, "p6": 12, "d6": 8, "r6": 6, "dg6": 1, "rg6": 1, "i6": 14, "o1": 123, "o2": 3, "o3": 3, "o4": 3}, "ME": {"id": 124, "s": 125, "p1": 126, "d1": 127, "r1": 128, "dg1": 1, "rg1": 1, "i1": 127, "p8": 4, "d8": 129, "r8": 130, "dg8": 1, "rg8": 1, "i8": 7, "p9": 4, "d9": 131, "r9": 6, "dg9": 1, "rg9": 1, "i9": 7, "p10": 4, "d10": 132, "r10": 6, "dg10": 0, "rg10": 1, "i10": 7, "p11": 4, "d11": 8, "r11": 6, "dg11": 1, "rg11": 1, "i11": 7, "p12": 4, "d12": 8, "r12": 6, "dg12": 1, "rg12": 1, "i12": 7, "p13": 4, "d13": 8, "r13": 6, "dg13": 1, "rg13": 1, "i13": 7, "p14": 4, "d14": 8, "r14": 6, "dg14": 1, "rg14": 1, "i14": 7, "p3": 126, "d3": 8, "r3": 6, "dg3": 1, "rg3": 1, "i3": 133, "p4": 126, "d4": 8, "r4": 6, "dg4": 1, "rg4": 1, "i4": 133, "p5": 126, "d5": 8, "r5": 6, "dg5": 1, "rg5": 1, "i5": 133, "p6": 126, "d6": 8, "r6": 6, "dg6": 1, "rg6": 1, "i6": 133, "p7": 4, "d7": 8, "r7": 134, "dg7": 1, "rg7": 1, "i7": 134, "o1": 135, "o2": 136, "o3": 137, "o4": 3}, "MI": {"id": 138, "s": 139, "p1": 12, "d1": 140, "r1": 141, "dg1": 1, "rg1": 1, "i1": 140, "p8": 12, "d8": 8, "r8": 141, "dg8": 1, "rg8": 1, "i8": 14, "p9": 12, "d9": 8, "r9": 142, "dg9": 1, "rg9": 0, "i9": 14, "p10": 12, "d10": 8, "r10": 6, "dg10": 1, "rg10": 1, "i10": 14, "p11": 12, "d11": 8, "r11": 6, "dg11": 1, "rg11": 1, "i11": 14, "p12": 12, "d12": 8, "r12": 6, "dg12": 1, "rg12": 1, "i12": 14, "p13": 12, "d13": 8, "r13": 6, "dg13": 1, "rg13": 1, "i13": 14, "p14": 12, "d14": 8, "r14": 6, "dg14": 1, "rg14": 1, "i14": 14, "p3": 12, "d3": 8, "r3": 6, "dg3": 1, "rg3": 1, "i3": 14, "p4": 12, "d4": 8, "r4": 6, "dg4": 1, "rg4": 1, "i4": 14, "p5": 12, "d5": 8, "r5": 6, "dg5": 1, "rg5": 1, "i5": 14, "p6": 12, "d6": 8, "r6": 6, "dg6": 1, "rg6": 1, "i6": 14, "p7": 12, "d7": 143, "r7": 6, "dg7": 1, "rg7": 1, "i7": 143, "o1": 144, "o2": 3, "o3": 3, "o4": 3}, "MN": {"id": 145, "s": 146, "p1": 12, "d1": 147, "r1": 148, "dg1": 1, "rg1": 1, "i1": 147, "p8": 12, "d8": 8, "r8": 149, "dg8": 1, "rg8": 1, "i8": 14, "p9": 12, "d9": 8, "r9": 6, "dg9": 1, "rg9": 1, "i9": 14, "p10": 12, "d10": 8, "r10": 6, "dg10": 1, "rg10": 1, "i10": 14, "p11": 12, "d11": 8, "r11": 6, "dg11": 1, "rg11": 1, "i11": 14, "p12": 12, "d12": 8, "r12": 6, "dg12": 1, "rg12": 1, "i12": 14, "p13": 12, "d13": 8, "r13": 6, "dg13": 1, "rg13": 1, "i13": 14, "p14": 12, "d14": 8, "r14": 6, "dg14": 1, "rg14": 1, "i14": 14, "p2": 150, "d2": 151, "r2": 152, "dg2": 1, "rg2": 1, "i2": 3, "p3": 12, "d3": 8, "r3": 6, "dg3": 1, "rg3": 1, "i3": 14, "p4": 12, "d4": 8, "r4": 6, "dg4": 1, "rg4": 1, "i4": 14, "p5": 12, "d5": 8, "r5": 6, "dg5": 1, "rg5": 1, "i5": 14, "p6": 12, "d6": 8, "r6": 6, "dg6": 1, "rg6": 1, "i6": 14, "p7": 12, "d7": 151, "r7": 6, "dg7": 1, "rg7": 1, "i7": 151, "o1": 153, "o2": 3, "o3": 3, "o4": 154}, "MO": {"id": 3, "s": 155, "p1": 12, "d1": 156, "r1": 157, "dg1": 1, "rg1": 1, "i1": 156, "p3": 12, "d3": 8, "r3": 6, "dg3": 1, "rg3": 1, "i3": 14, "p4": 12, "d4": 8, "r4": 6, "dg4": 1, "rg4": 1, "i4": 14, "p5": 12, "d5": 8, "r5": 6, "dg5": 1, "rg5": 1, "i5": 14, "p6": 12, "d6": 8, "r6": 6, "dg6": 1, "rg6": 1, "i6": 14, "o1": 158, "o2": 159, "o3": 160, "o4": 3}, "MS": {"id": 161, "s": 162, "p1": 4, "d1": 163, "r1": 164, "dg1": 1, "rg1": 1, "i1": 164, "p8": 4, "d8": 165, "r8": 6, "dg8": 1, "rg8": 1, "i8": 7, "p9": 4, "d9": 8, "r9": 6, "dg9": 1, "rg9": 1, "i9": 7, "p10": 4, "d10": 8, "r10": 6, "dg10": 1, "rg10": 1, "i10": 7, "p11": 4, "d11": 8, "r11": 6, "dg11": 1, "rg11": 1, "i11": 7, "p12": 4, "d12": 8, "r12": 6, "dg12": 1, "rg12": 1, "i12": 7, "p13": 4, "d13": 8, "r13": 6, "dg13": 1, "rg13": 1, "i13": 7, "p14": 4, "d14": 8, "r14": 6, "dg14": 1, "rg14": 1, "i14": 7, "p2": 150, "d2": 165, "r2": 166, "dg2": 1, "rg2": 1, "i2": 3, "p3": 4, "d3": 8, "r3": 6, "dg3": 1, "rg3": 1, "i3": 7, "p4": 4, "d4": 8, "r4": 6, "dg4": 1, "rg4": 1, "i4": 7, "p5": 4, "d5": 8, "r5": 6, "dg5": 1, "rg5": 1, "i5": 7, "p6": 4, "d6": 8, "r6": 6, "dg6": 1, "rg6": 1, "i6": 7, "p7": 4, "d7": 8, "r7": 166, "dg7": 1, "rg7": 1, "i7": 166, "o1": 167, "o2": 168, "o3": 3, "o4": 3}, "MT": {"id": 169, "s": 170, "p1": 12, "d1": 171, "r1": 172, "dg1": 1, "rg1": 1, "i1": 171, "p8": 4, "d8": 173, "r8": 6, "dg8": 1, "rg8": 1, "i8": 7, "p9": 4, "d9": 174, "r9": 6, "dg9": 1, "rg9": 1, "i9": 7, "p10": 4, "d10": 175, "r10": 6, "dg10": 0, "rg10": 1, "i10": 7, "p11": 4, "d11": 176, "r11": 6, "dg11": 1, "rg11": 1, "i11": 7, "p12": 4, "d12": 8, "r12": 6, "dg12": 1, "rg12": 1, "i12": 7, "p13": 4, "d13": 8, "r13": 6, "dg13": 1, "rg13": 1, "i13": 7, "p14": 4, "d14": 8, "r14": 6, "dg14": 1, "rg14": 1, "i14": 7, "p3": 12, "d3": 8, "r3": 6, "dg3": 1, "rg3": 1, "i3": 14, "p4": 12, "d4": 8, "r4": 6, "dg4": 1, "rg4": 1, "i4": 14, "p5": 12, "d5": 8, "r5": 6, "dg5": 1, "rg5": 1, "i5": 14, "p6": 12, "d6": 8, "r6": 6, "dg6": 1, "rg6": 1, "i6": 14, "p7": 4, "d7": 8, "r7": 177, "dg7": 1, "rg7": 1, "i7": 177, "o1": 3, "o2": 178, "o3": 3, "o4": 3}, "NC": {"id": 179, "s": 180, "p1": 2, "d1": 3, "r1": 3, "dg1": 1, "rg1": 1, "i1": 3, "p8": 4, "d8": 181, "r8": 182, "dg8": 1, "rg8": 0, "i8": 7, "p9": 4, "d9": 183, "r9": 6, "dg9": 1, "rg9": 1, "i9": 7, "p10": 4, "d10": 184, "r10": 6, "dg10": 0, "rg10": 1, "i10": 7, "p11": 4, "d11": 8, "r11": 6, "dg11": 1, "rg11": 1, "i11": 7, "p12": 4, "d12": 8, "r12": 6, "dg12": 1, "rg12": 1, "i12": 7, "p13": 4, "d13": 8, "r13": 6, "dg13": 1, "rg13": 1, "i13": 7, "p14": 4, "d14": 8, "r14": 6, "dg14": 1, "rg14": 1, "i14": 7, "p3": 2, "d3": 3, "r3": 3, "dg3": 1, "rg3": 1, "i3": 3, "p4": 2, "d4": 3, "r4": 3, "dg4": 1, "rg4": 1, "i4": 3, "p5": 2, "d5": 3, "r5": 3, "dg5": 1, "rg5": 1, "i5": 3, "p6": 2, "d6": 3, "r6": 3, "dg6": 1, "rg6": 1, "i6": 3, "p7": 4, "d7": 8, "r7": 185, "dg7": 1, "rg7": 1, "i7": 185, "o1": 3, "o2": 3, "o3": 3, "o4": 3}, "ND": {"id": 3, "s": 186, "p1": 12, "d1": 187, "r1": 188, "dg1": 1, "rg1": 1, "i1": 187, "p3": 12, "d3": 8, "r3": 6, "dg3": 1, "rg3": 1, "i3": 14, "p4": 12, "d4": 8, "r4": 6, "dg4": 1, "rg4": 1, "i4": 14, "p5": 12, "d5": 8, "r5": 6, "dg5": 1, "rg5": 1, "i5": 14, "p6": 12, "d6": 8, "r6": 6, "dg6": 1, "rg6": 1, "i6": 14, "o1": 3, "o2": 3, "o3": 3, "o4": 3}, "NE": {"id": 189, "s": 190, "p1": 4, "d1": 191, "r1": 192, "dg1": 1, "rg1": 1, "i1": 192, "p8": 4, "d8": 193, "r8": 194, "dg8": 1, "rg8": 1, "i8": 7, "p9": 4, "d9": 8, "r9": 6, "dg9": 1, "rg9": 1, "i9": 7, "p10": 4, "d10": 8, "r10": 6, "dg10": 1, "rg10": 1, "i10": 7, "p11": 4, "d11": 8, "r11": 6, "dg11": 1, "rg11": 1, "i11": 7, "p12": 4, "d12": 8, "r12": 6, "dg12": 1, "rg12": 1, "i12": 7, "p13": 4, "d13": 8, "r13": 6, "dg13": 1, "rg13": 1, "i13": 7, "p14": 4, "d14": 8, "r14": 6, "dg14": 1, "rg14": 1, "i14": 7, "p3": 4, "d3": 8, "r3": 6, "dg3": 1, "rg3": 1, "i3": 7, "p4": 4, "d4": 8, "r4": 6, "dg4": 1, "rg4": 1, "i4": 7, "p5": 4, "d5": 8, "r5": 6, "dg5": 1, "rg5": 1, "i5": 7, "p6": 4, "d6": 8, "r6": 6, "dg6": 1, "rg6": 1, "i6": 7, "p7": 4, "d7": 8, "r7": 195, "dg7": 1, "rg7": 1, "i7": 195, "o1": 3, "o2": 3, "o3": 3, "o4": 3}, "NH": {"id": 196, "s": 197, "p1": 2, "d1": 3, "r1": 3, "dg1": 1, "rg1": 1, "i1": 3, "p8": 12, "d8": 8, "r8": 198, "dg8": 1, "rg8": 1, "i8": 14, "p9": 12, "d9": 8, "r9": 199, "dg9": 1, "rg9": 1, "i9": 14, "p10": 12, "d10": 8, "r10": 200, "dg10": 1, "rg10": 0, "i10": 14, "p11": 12, "d11": 8, "r11": 6, "dg11": 1, "rg11": 1, "i11": 14, "p12": 12, "d12": 8, "r12": 6, "dg12": 1, "rg12": 1, "i12": 14, "p13": 12, "d13": 8, "r13": 6, "dg13": 1, "rg13": 1, "i13": 14, "p14": 12, "d14": 8, "r14": 6, "dg14": 1, "rg14": 1, "i14": 14, "p3": 2, "d3": 3, "r3": 3, "dg3": 1, "rg3": 1, "i3": 3, "p4": 2, "d4": 3, "r4": 3, "dg4": 1, "rg4": 1, "i4": 3, "p5": 2, "d5": 3, "r5": 3, "dg5": 1, "rg5": 1, "i5": 3, "p6": 2, "d6": 3, "r6": 3, "dg6": 1, "rg6": 1, "i6": 3, "p7": 12, "d7": 201, "r7": 6, "dg7": 1, "rg7": 1, "i7": 201, "o1": 3, "o2": 3, "o3": 3, "o4": 3}, "NJ": {"id": 202, "s": 203, "p1": 12, "d1": 204, "r1": 205, "dg1": 1, "rg1": 1, "i1": 204, "p8": 12, "d8": 8, "r8": 206, "dg8": 1, "rg8": 1, "i8": 14, "p9": 12, "d9": 8, "r9": 6, "dg9": 1, "rg9": 1, "i9": 14, "p10": 12, "d10": 8, "r10": 6, "dg10": 1, "rg10": 1, "i10": 14, "p11": 12, "d11": 8, "r11": 6, "dg11": 1, "rg11": 1, "i11": 14, "p12": 12, "d12": 8, "r12": 6, "dg12": 1, "rg12": 1, "i12": 14, "p13": 12, "d13": 8, "r13": 6, "dg13": 1, "rg13": 1, "i13": 14, "p14": 12, "d14": 8, "r14": 6, "dg14": 1, "rg14": 1, "i14": 14, "p3": 12, "d3": 8, "r3": 6, "dg3": 1, "rg3": 1, "i3": 14, "p4": 12, "d4": 8, "r4": 6, "dg4": 1, "rg4": 1, "i4": 14, "p5": 12, "d5": 8, "r5": 6, "dg5": 1, "rg5": 1, "i5": 14, "p6": 12, "d6": 8, "r6": 6, "dg6": 1, "rg6": 1, "i6": 14, "p7": 12, "d7": 207, "r7": 6, "dg7": 1, "rg7": 1, "i7": 207, "o1": 208, "o2": 209, "o3": 210, "o4": 3}, "NM": {"id": 211, "s": 212, "p1": 12, "d1": 213, "r1": 214, "dg1": 1, "rg1": 1, "i1": 213, "p8": 12, "d8": 215, "r8": 216, "dg8": 1, "rg8": 1, "i8": 14, "p9": 12, "d9": 8, "r9": 214, "dg9": 1, "rg9": 1, "i9": 14, "p10": 12, "d10": 8, "r10": 217, "dg10": 1, "rg10": 0, "i10": 14, "p11": 12, "d11": 8, "r11": 6, "dg11": 1, "rg11": 1, "i11": 14, "p12": 12, "d12": 8, "r12": 6, "dg12": 1, "rg12": 1, "i12": 14, "p13": 12, "d13": 8, "r13": 6, "dg13": 1, "rg13": 1, "i13": 14, "p14": 12, "d14": 8, "r14": 6, "dg14": 1, "rg14": 1, "i14": 14, "p3": 12, "d3": 8, "r3": 6, "dg3": 1, "rg3": 1, "i3": 14, "p4": 12, "d4": 8, "r4": 6, "dg4": 1, "rg4": 1, "i4": 14, "p5": 12, "d5": 8, "r5": 6, "dg5": 1, "rg5": 1, "i5": 14, "p6": 12, "d6": 8, "r6": 6, "dg6": 1, "rg6": 1, "i6": 14, "p7": 12, "d7": 8, "r7": 6, "dg7": 1, "rg7": 1, "i7": 218, "o1": 219, "o2": 3, "o3": 3, "o4": 3}, "NV": {"id": 3, "s": 220, "p1": 4, "d1": 221, "r1": 222, "dg1": 1, "rg1": 1, "i1": 222, "p3": 4, "d3": 8, "r3": 6, "dg3": 1, "rg3": 1, "i3": 7, "p4": 4, "d4": 8, "r4": 6, "dg4": 1, "rg4": 1, "i4": 7, "p5": 4, "d5": 8, "r5": 6, "dg5": 1, "rg5": 1, "i5": 7, "p6": 4, "d6": 8, "r6": 6, "dg6": 1, "rg6": 1, "i6": 7, "o1": 223, "o2": 224, "o3": 225, "o4": 3}, "NY": {"id": 3, "s": 226, "p1": 12, "d1": 227, "r1": 228, "dg1": 1, "rg1": 1, "i1": 227, "p3": 12, "d3": 8, "r3": 6, "dg3": 1, "rg3": 1, "i3": 14, "p4": 12, "d4": 8, "r4": 6, "dg4": 1, "rg4": 1, "i4": 14, "p5": 12, "d5": 8, "r5": 6, "dg5": 1, "rg5": 1, "i5": 14, "p6": 12, "d6": 8, "r6": 6, "dg6": 1, "rg6": 1, "i6": 14, "o1": 3, "o2": 3, "o3": 3, "o4": 3}, "OH": {"id": 3, "s": 229, "p1": 12, "d1": 230, "r1": 231, "dg1": 1, "rg1": 1, "i1": 230, "p3": 12, "d3": 8, "r3": 6, "dg3": 1, "rg3": 1, "i3": 14, "p4": 12, "d4": 8, "r4": 6, "dg4": 1, "rg4": 1, "i4": 14, "p5": 12, "d5": 8, "r5": 6, "dg5": 1, "rg5": 1, "i5": 14, "p6": 12, "d6": 8, "r6": 6, "dg6": 1, "rg6": 1, "i6": 14, "o1": 232, "o2": 3, "o3": 3, "o4": 3}, "OK": {"id": 233, "s": 234, "p1": 2, "d1": 3, "r1": 3, "dg1": 1, "rg1": 1, "i1": 3, "p8": 4, "d8": 235, "r8": 6, "dg8": 1, "rg8": 1, "i8": 7, "p9": 4, "d9": 236, "r9": 6, "dg9": 1, "rg9": 1, "i9": 7, "p10": 4, "d10": 8, "r10": 6, "dg10": 1, "rg10": 1, "i10": 7, "p11": 4, "d11": 8, "r11": 6, "dg11": 1, "rg11": 1, "i11": 7, "p12": 4, "d12": 8, "r12": 6, "dg12": 1, "rg12": 1, "i12": 7, "p13": 4, "d13": 8, "r13": 6, "dg13": 1, "rg13": 1, "i13": 7, "p14": 4, "d14": 8, "r14": 6, "dg14": 1, "rg14": 1, "i14": 7, "p3": 2, "d3": 3, "r3": 3, "dg3": 1, "rg3": 1, "i3": 3, "p4": 2, "d4": 3, "r4": 3, "dg4": 1, "rg4": 1, "i4": 3, "p5": 2, "d5": 3, "r5": 3, "dg5": 1, "rg5": 1, "i5": 3, "p6": 2, "d6": 3, "r6": 3, "dg6": 1, "rg6": 1, "i6": 3, "p7": 4, "d7": 8, "r7": 237, "dg7": 1, "rg7": 1, "i7": 237, "o1": 3, "o2": 3, "o3": 3, "o4": 3}, "OR": {"id": 238, "s": 239, "p1": 2, "d1": 3, "r1": 3, "dg1": 1, "rg1": 1, "i1": 3, "p8": 12, "d8": 8, "r8": 240, "dg8": 1, "rg8": 1, "i8": 14, "p9": 12, "d9": 8, "r9": 6, "dg9": 1, "rg9": 1, "i9": 14, "p10": 12, "d10": 8, "r10": 6, "dg10": 1, "rg10": 1, "i10": 14, "p11": 12, "d11": 8, "r11": 6, "dg11": 1, "rg11": 1, "i11": 14, "p12": 12, "d12": 8, "r12": 6, "dg12": 1, "rg12": 1, "i12": 14, "p13": 12, "d13": 8, "r13": 6, "dg13": 1, "rg13": 1, "i13": 14, "p14": 12, "d14": 8, "r14": 6, "dg14": 1, "rg14": 1, "i14": 14, "p3": 2, "d3": 3, "r3": 3, "dg3": 1, "rg3": 1, "i3": 3, "p4": 2, "d4": 3, "r4": 3, "dg4": 1, "rg4": 1, "i4": 3, "p5": 2, "d5": 3, "r5": 3, "dg5": 1, "rg5": 1, "i5": 3, "p6": 2, "d6": 3, "r6": 3, "dg6": 1, "rg6": 1, "i6": 3, "p7": 12, "d7": 241, "r7": 6, "dg7": 1, "rg7": 1, "i7": 241, "o1": 3, "o2": 3, "o3": 3, "o4": 3}, "PA": {"id": 3, "s": 242, "p1": 12, "d1": 243, "r1": 244, "dg1": 1, "rg1": 1, "i1": 243, "p3": 12, "d3": 8, "r3": 6, "dg3": 1, "rg3": 1, "i3": 14, "p4": 12, "d4": 8, "r4": 6, "dg4": 1, "rg4": 1, "i4": 14, "p5": 12, "d5": 8, "r5": 6, "dg5": 1, "rg5": 1, "i5": 14, "p6": 12, "d6": 8, "r6": 6, "dg6": 1, "rg6": 1, "i6": 14, "o1": 245, "o2": 246, "o3": 3, "o4": 3}, "RI": {"id": 247, "s": 248, "p1": 12, "d1": 249, "r1": 250, "dg1": 1, "rg1": 1, "i1": 249, "p8": 12, "d8": 8, "r8": 6, "dg8": 1, "rg8": 1, "i8": 14, "p9": 12, "d9": 8, "r9": 6, "dg9": 1, "rg9": 1, "i9": 14, "p10": 12, "d10": 8, "r10": 6, "dg10": 1, "rg10": 1, "i10": 14, "p11": 12, "d11": 8, "r11": 6, "dg11": 1, "rg11": 1, "i11": 14, "p12": 12, "d12": 8, "r12": 6, "dg12": 1, "rg12": 1, "i12": 14, "p13": 12, "d13": 8, "r13": 6, "dg13": 1, "rg13": 1, "i13": 14, "p14": 12, "d14": 8, "r14": 6, "dg14": 1, "rg14": 1, "i14": 14, "p3": 12, "d3": 8, "r3": 6, "dg3": 1, "rg3": 1, "i3": 14, "p4": 12, "d4": 8, "r4": 6, "dg4": 1, "rg4": 1, "i4": 14, "p5": 12, "d5": 8, "r5": 6, "dg5": 1, "rg5": 1, "i5": 14, "p6": 12, "d6": 8, "r6": 6, "dg6": 1, "rg6": 1, "i6": 14, "p7": 12, "d7": 251, "r7": 6, "dg7": 1, "rg7": 1, "i7": 251, "o1": 3, "o2": 3, "o3": 3, "o4": 3}, "SC": {"id": 252, "s": 253, "p1": 2, "d1": 3, "r1": 3, "dg1": 1, "rg1": 1, "i1": 3, "p8": 4, "d8": 254, "r8": 255, "dg8": 1, "rg8": 0, "i8": 7, "p9": 4, "d9": 256, "r9": 6, "dg9": 0, "rg9": 1, "i9": 7, "p10": 4, "d10": 8, "r10": 6, "dg10": 1, "rg10": 1, "i10": 7, "p11": 4, "d11": 8, "r11": 6, "dg11": 1, "rg11": 1, "i11": 7, "p12": 4, "d12": 8, "r12": 6, "dg12": 1, "rg12": 1, "i12": 7, "p13": 4, "d13": 8, "r13": 6, "dg13": 1, "rg13": 1, "i13": 7, "p14": 4, "d14": 8, "r14": 6, "dg14": 1, "rg14": 1, "i14": 7, "p3": 2, "d3": 3, "r3": 3, "dg3": 1, "rg3": 1, "i3": 3, "p4": 2, "d4": 3, "r4": 3, "dg4": 1, "rg4": 1, "i4": 3, "p5": 2, "d5": 3, "r5": 3, "dg5": 1, "rg5": 1, "i5": 3, "p6": 2, "d6": 3, "r6": 3, "dg6": 1, "rg6": 1, "i6": 3, "p7": 4, "d7": 8, "r7": 257, "dg7": 1, "rg7": 1, "i7": 257, "o1": 3, "o2": 3, "o3": 3, "o4": 3}, "SD": {"id": 258, "s": 259, "p1": 2, "d1": 3, "r1": 3, "dg1": 1, "rg1": 1, "i1": 3, "p8": 4, "d8": 260, "r8": 261, "dg8": 1, "rg8": 1, "i8": 7, "p9": 4, "d9": 8, "r9": 6, "dg9": 1, "rg9": 1, "i9": 7, "p10": 4, "d10": 8, "r10": 6, "dg10": 1, "rg10": 1, "i10": 7, "p11": 4, "d11": 8, "r11": 6, "dg11": 1, "rg11": 1, "i11": 7, "p12": 4, "d12": 8, "r12": 6, "dg12": 1, "rg12": 1, "i12": 7, "p13": 4, "d13": 8, "r13": 6, "dg13": 1, "rg13": 1, "i13": 7, "p14": 4, "d14": 8, "r14": 6, "dg14": 1, "rg14": 1, "i14": 7, "p3": 2, "d3": 3, "r3": 3, "dg3": 1, "rg3": 1, "i3": 3, "p4": 2, "d4": 3, "r4": 3, "dg4": 1, "rg4": 1, "i4": 3, "p5": 2, "d5": 3, "r5": 3, "dg5": 1, "rg5": 1, "i5": 3, "p6": 2, "d6": 3, "r6": 3, "dg6": 1, "rg6": 1, "i6": 3, "p7": 4, "d7": 8, "r7": 262, "dg7": 1, "rg7": 1, "i7": 262, "o1": 3, "o2": 3, "o3": 3, "o4": 3}, "TN": {"id": 263, "s": 264, "p1": 4, "d1": 265, "r1": 266, "dg1": 1, "rg1": 1, "i1": 267, "p8": 4, "d8": 268, "r8": 269, "dg8": 1, "rg8": 0, "i8": 7, "p9": 4, "d9": 270, "r9": 271, "dg9": 1, "rg9": 0, "i9": 7, "p10": 4, "d10": 8, "r10": 272, "dg10": 1, "rg10": 0, "i10": 7, "p11": 4, "d11": 8, "r11": 6, "dg11": 1, "rg11": 1, "i11": 7, "p12": 4, "d12": 8, "r12": 6, "dg12": 1, "rg12": 1, "i12": 7, "p13": 4, "d13": 8, "r13": 6, "dg13": 1, "rg13": 1, "i13": 7, "p14": 4, "d14": 8, "r14": 6, "dg14": 1, "rg14": 1, "i14": 7, "p3": 4, "d3": 8, "r3": 6, "dg3": 1, "rg3": 1, "i3": 7, "p4": 4, "d4": 8, "r4": 6, "dg4": 1, "rg4": 1, "i4": 7, "p5": 4, "d5": 8, "r5": 6, "dg5": 1, "rg5": 1, "i5": 7, "p6": 4, "d6": 8, "r6": 6, "dg6": 1, "rg6": 1, "i6": 7, "p7": 4, "d7": 8, "r7": 6, "dg7": 1, "rg7": 1, "i7": 273, "o1": 274, "o2": 275, "o3": 276, "o4": 3}, "TX": {"id": 277, "s": 278, "p1": 4, "d1": 279, "r1": 280, "dg1": 1, "rg1": 1, "i1": 280, "p8": 4, "d8": 281, "r8": 282, "dg8": 0, "rg8": 0, "i8": 7, "p9": 4, "d9": 283, "r9": 6, "dg9": 1, "rg9": 1, "i9": 7, "p10": 4, "d10": 284, "r10": 6, "dg10": 1, "rg10": 1, "i10": 7, "p11": 4, "d11": 285, "r11": 6, "dg11": 1, "rg11": 1, "i11": 7, "p12": 4, "d12": 286, "r12": 6, "dg12": 1, "rg12": 1, "i12": 7, "p13": 4, "d13": 8, "r13": 6, "dg13": 1, "rg13": 1, "i13": 7, "p14": 4, "d14": 8, "r14": 6, "dg14": 1, "rg14": 1, "i14": 7, "p3": 4, "d3": 8, "r3": 6, "dg3": 1, "rg3": 1, "i3": 7, "p4": 4, "d4": 8, "r4": 6, "dg4": 1, "rg4": 1, "i4": 7, "p5": 4, "d5": 8, "r5": 6, "dg5": 1, "rg5": 1, "i5": 7, "p6": 4, "d6": 8, "r6": 6, "dg6": 1, "rg6": 1, "i6": 7, "p7": 4, "d7": 8, "r7": 287, "dg7": 1, "rg7": 1, "i7": 287, "o1": 288, "o2": 3, "o3": 3, "o4": 3}, "UT": {"id": 3, "s": 289, "p1": 4, "d1": 290, "r1": 291, "dg1": 1, "rg1": 1, "i1": 292, "p3": 4, "d3": 8, "r3": 6, "dg3": 1, "rg3": 1, "i3": 7, "p4": 4, "d4": 8, "r4": 6, "dg4": 1, "rg4": 1, "i4": 7, "p5": 4, "d5": 8, "r5": 6, "dg5": 1, "rg5": 1, "i5": 7, "p6": 4, "d6": 8, "r6": 6, "dg6": 1, "rg6": 1, "i6": 7, "o1": 293, "o2": 3, "o3": 3, "o4": 3}, "VA": {"id": 294, "s": 295, "p1": 12, "d1": 296, "r1": 297, "dg1": 1, "rg1": 1, "i1": 296, "p8": 12, "d8": 8, "r8": 298, "dg8": 1, "rg8": 1, "i8": 14, "p9": 12, "d9": 8, "r9": 6, "dg9": 1, "rg9": 1, "i9": 14, "p10": 12, "d10": 8, "r10": 6, "dg10": 1, "rg10": 1, "i10": 14, "p11": 12, "d11": 8, "r11": 6, "dg11": 1, "rg11": 1, "i11": 14, "p12": 12, "d12": 8, "r12": 6, "dg12": 1, "rg12": 1, "i12": 14, "p13": 12, "d13": 8, "r13": 6, "dg13": 1, "rg13": 1, "i13": 14, "p14": 12, "d14": 8, "r14": 6, "dg14": 1, "rg14": 1, "i14": 14, "p3": 12, "d3": 8, "r3": 6, "dg3": 1, "rg3": 1, "i3": 14, "p4": 12, "d4": 8, "r4": 6, "dg4": 1, "rg4": 1, "i4": 14, "p5": 12, "d5": 8, "r5": 6, "dg5": 1, "rg5": 1, "i5": 14, "p6": 12, "d6": 8, "r6": 6, "dg6": 1, "rg6": 1, "i6": 14, "p7": 12, "d7": 299, "r7": 6, "dg7": 1, "rg7": 1, "i7": 299, "o1": 300, "o2": 3, "o3": 3, "o4": 3}, "VT": {"id": 301, "s": 302, "p1": 126, "d1": 303, "r1": 304, "dg1": 1, "rg1": 1, "i1": 305, "p3": 126, "d3": 8, "r3": 6, "dg3": 1, "rg3": 1, "i3": 133, "p4": 126, "d4": 8, "r4": 6, "dg4": 1, "rg4": 1, "i4": 133, "p5": 126, "d5": 8, "r5": 6, "dg5": 1, "rg5": 1, "i5": 133, "p6": 126, "d6": 8, "r6": 6, "dg6": 1, "rg6": 1, "i6": 133, "o1": 3, "o2": 3, "o3": 3, "o4": 3}, "WA": {"id": 3, "s": 306, "p1": 12, "d1": 307, "r1": 308, "dg1": 1, "rg1": 1, "i1": 307, "p3": 12, "d3": 8, "r3": 6, "dg3": 1, "rg3": 1, "i3": 14, "p4": 12, "d4": 8, "r4": 6, "dg4": 1, "rg4": 1, "i4": 14, "p5": 12, "d5": 8, "r5": 6, "dg5": 1, "rg5": 1, "i5": 14, "p6": 12, "d6": 8, "r6": 6, "dg6": 1, "rg6": 1, "i6": 14, "o1": 3, "o2": 3, "o3": 3, "o4": 3}, "WI": {"id": 3, "s": 309, "p1": 12, "d1": 310, "r1": 311, "dg1": 1, "rg1": 1, "i1": 310, "p3": 12, "d3": 8, "r3": 6, "dg3": 1, "rg3": 1, "i3": 14, "p4": 12, "d4": 8, "r4": 6, "dg4": 1, "rg4": 1, "i4": 14, "p5": 12, "d5": 8, "r5": 6, "dg5": 1, "rg5": 1, "i5": 14, "p6": 12, "d6": 8, "r6": 6, "dg6": 1, "rg6": 1, "i6": 14, "o1": 3, "o2": 3, "o3": 3, "o4": 3}, "WV": {"id": 312, "s": 313, "p1": 12, "d1": 314, "r1": 315, "dg1": 1, "rg1": 1, "i1": 314, "p8": 4, "d8": 316, "r8": 317, "dg8": 1, "rg8": 1, "i8": 7, "p9": 4, "d9": 318, "r9": 6, "dg9": 1, "rg9": 1, "i9": 7, "p10": 4, "d10": 8, "r10": 6, "dg10": 1, "rg10": 1, "i10": 7, "p11": 4, "d11": 8, "r11": 6, "dg11": 1, "rg11": 1, "i11": 7, "p12": 4, "d12": 8, "r12": 6, "dg12": 1, "rg12": 1, "i12": 7, "p13": 4, "d13": 8, "r13": 6, "dg13": 1, "rg13": 1, "i13": 7, "p14": 4, "d14": 8, "r14": 6, "dg14": 1, "rg14": 1, "i14": 7, "p3": 12, "d3": 8, "r3": 6, "dg3": 1, "rg3": 1, "i3": 14, "p4": 12, "d4": 8, "r4": 6, "dg4": 1, "rg4": 1, "i4": 14, "p5": 12, "d5": 8, "r5": 6, "dg5": 1, "rg5": 1, "i5": 14, "p6": 12, "d6": 8, "r6": 6, "dg6": 1, "rg6": 1, "i6": 14, "p7": 4, "d7": 8, "r7": 319, "dg7": 1, "rg7": 1, "i7": 319, "o1": 3, "o2": 3, "o3": 3, "o4": 3}, "WY": {"id": 320, "s": 321, "p1": 4, "d1": 322, "r1": 323, "dg1": 1, "rg1": 1, "i1": 323, "p8": 4, "d8": 324, "r8": 325, "dg8": 0, "rg8": 1, "i8": 7, "p9": 4, "d9": 8, "r9": 326, "dg9": 1, "rg9": 1, "i9": 7, "p10": 4, "d10": 8, "r10": 327, "dg10": 1, "rg10": 0, "i10": 7, "p11": 4, "d11": 8, "r11": 6, "dg11": 1, "rg11": 1, "i11": 7, "p12": 4, "d12": 8, "r12": 6, "dg12": 1, "rg12": 1, "i12": 7, "p13": 4, "d13": 8, "r13": 6, "dg13": 1, "rg13": 1, "i13": 7, "p14": 4, "d14": 8, "r14": 6, "dg14": 1, "rg14": 1, "i14": 7, "p3": 4, "d3": 8, "r3": 6, "dg3": 1, "rg3": 1, "i3": 7, "p4": 4, "d4": 8, "r4": 6, "dg4": 1, "rg4": 1, "i4": 7, "p5": 4, "d5": 8, "r5": 6, "dg5": 1, "rg5": 1, "i5": 7, "p6": 4, "d6": 8, "r6": 6, "dg6": 1, "rg6": 1, "i6": 7, "p7": 4, "d7": 8, "r7": 6, "dg7": 1, "rg7": 1, "i7": 328, "o1": 329, "o2": 3, "o3": 3, "o4": 3}}, "values": {"0": "Independent Tony Knowles", "1": "AK", "2": " V", "3": "_none_", "4": "R", "5": "Democrat Al Gross", "6": "A Republican Candidate", "7": "Republican _none_", "8": "A Democratic Candidate", "9": "Republican Dan Sullivan", "10": "Independent Robert Bentley", "11": "AL", "12": "D", "13": "Republican Bradley Byrne", "14": "Democrat _none_", "15": "Republican Tommy Tuberville", "16": "Republican Arnold Mooney", "17": "Republican Roy Moore", "18": "Republican Jeff Sessions", "19": "Republican Stanley Adair", "20": "Democrat Doug Jones", "21": "Independent Mike Beebe", "22": "AR", "23": "Republican Tom Cotton", "24": "Independent Janet Napolitano", "25": "AZ", "26": "Democrat Kyrsten Sinema", "27": "Republican Martha McSally", "28": "Republican Jeff Flake", "29": "Democrat Mark Kelly", "30": "Republican Daniel McCarthy", "31": "Libertarian Doug Marks", "32": "Green Party candidate Angela Green", "33": "CA", "34": "Democrat Dianne Feinstein", "35": "Democrat Kevin de Le\u00f3n", "36": "Independent Bill Owens", "37": "CO", "38": "Democrat John Hickenlooper", "39": "Democrat Andrew Romanoff", "40": "Democrat Stephany Rose Spaulding", "41": "Democrat Michelle Warren", "42": "Democrat Lorena Garcia", "43": "Republican Cory Gardner", "44": "CT", "45": "Democrat Chris Murphy", "46": "Republican Matthew Corey", "47": "Independent Mike Castle", "48": "DE", "49": "Democrat Tom Carper", "50": "Republican Gene Truono", "51": "Democrat Jess Scarane", "52": "Democrat Chris Coons", "53": "FL", "54": "Democrat Bill Nelson", "55": "Republican Rick Scott", "56": "Libertarian Joe Wendt", "57": "Independent Max Cleland", "58": "GA", "59": "Democrat Teresa Tomlinson", "60": "Democrat Jon Ossoff", "61": "Democrat Sarah Riggs Amico", "62": "Democrat Maya Dillard Smith", "63": "Republican David Perdue", "64": "HI", "65": "Democrat Mazie Hirono", "66": "Republican Thomas White", "67": "Independent Arturo Reyes", "68": "Independent Tom Harkin", "69": "IA", "70": "Democrat Eddie J. Mauro", "71": "Democrat Michael Franken", "72": "Democrat Theresa Greenfield", "73": "Democrat Kimberly Graham", "74": "Republican Joni Ernst", "75": "Independent Walt Minnick", "76": "ID", "77": "Democrat Nancy Harris", "78": "Democrat Travis Oler", "79": "Democrat James Vandermaas", "80": "Republican Jim Risch", "81": "Independent Mark Kirk", "82": "IL", "83": "Democrat Marilyn Jordan Lawlor", "84": "Republican Mark Curran", "85": "Republican Omeed Memar", "86": "Republican Casey Chlebek", "87": "Republican Thomas Tarter", "88": "Democrat Dick Durbin", "89": "IN", "90": "Democrat Joe Donnelly", "91": "Republican Mike Braun", "92": "Libertarian Lucy Brenton", "93": "Independent Bill Graves", "94": "KS", "95": "Democrat Barbara Bollier", "96": "Republican Kris Kobach", "97": "Democrat Usha Reddi", "98": "Republican Susan Wagle", "99": "Republican Bryan Pruitt", "100": "Republican Roger Marshall", "101": "Republican Pat Roberts", "102": "Independent Steve Beshear", "103": "KY", "104": "Democrat Amy McGrath", "105": "Republican Mitch McConnell", "106": "Independent Buddy Roemer", "107": "LA", "108": "Democrat Antoine Pierce", "109": "Republican Bill Cassidy", "110": "Independent Bill Weld", "111": "MA", "112": "Democrat Elizabeth Warren", "113": "Republican Geoff Diehl", "114": "Democrat Joe Kennedy", "115": "Republican Shiva Ayyadurai", "116": "Democrat Shannon Liss-Riordan", "117": "Democrat Steve Pemberton", "118": "Democrat Ed Markey", "119": "Independent Shiva Ayyadurai", "120": "MD", "121": "Democrat Ben Cardin", "122": "Republican Tony Campbell", "123": "Libertarian Arvin Vohra", "124": "Independent Jock McKernan", "125": "ME", "126": "I", "127": "Independent Angus King", "128": "Republican Eric Brakey", "129": "Democrat Sara Gideon", "130": "Republican Nick Isgro", "131": "Democrat Betsy Sweet", "132": "Democrat Ross LaJeunesse", "133": "Independent _none_", "134": "Republican Susan Collins", "135": "Democrat Zak Ringelstein", "136": "Independent Benjamin Pollard", "137": "Libertarian Chris Lyons", "138": "Independent John Amash", "139": "MI", "140": "Democrat Debbie Stabenow", "141": "Republican John James", "142": "Republican Bob Carr", "143": "Democrat Gary Peters", "144": "Independent Marcia Squier", "145": "Independent Tim Pawlenty", "146": "MN", "147": "Democrat Amy Klobuchar", "148": "Republican Jim Newberger", "149": "Republican Jason Lewis", "150": "none", "151": "Democrat Tina Smith", "152": "Republican Karin Housley", "153": "Green Party candidate Paula Overby", "154": "Legal Marijuana Now Party candidate Sarah Wellington", "155": "MO", "156": "Democrat Claire McCaskill", "157": "Republican Josh Hawley", "158": "Green Party candidate Jerome Bauer", "159": "Libertarian Japheth Campbell", "160": "Independent Craig O'Dear", "161": "Independent Jim Hood", "162": "MS", "163": "Democrat David Baria", "164": "Republican Roger Wicker", "165": "Democrat Mike Espy", "166": "Republican Cindy Hyde-Smith", "167": "Libertarian Danny Bedwell", "168": "Reform party candidate Shawn O'Hara", "169": "Independent Marc Racicot", "170": "MT", "171": "Democrat Jon Tester", "172": "Republican Matt Rosendale", "173": "Democrat Steve Bullock", "174": "Democrat Wilmot Collins", "175": "Democrat John Mues", "176": "Democrat Cora Neumann", "177": "Republican Steve Daines", "178": "Libertarian Rick Breckenridge", "179": "Independent Jim Hunt", "180": "NC", "181": "Democrat Cal Cunningham", "182": "Republican Sandy Smith", "183": "Democrat Erica Smith", "184": "Democrat Trevor Fuller", "185": "Republican Thom Tillis", "186": "ND", "187": "Democrat Heidi Heitkamp", "188": "Republican Kevin Cramer", "189": "Independent Chuck Hagel", "190": "NE", "191": "Democrat Jane Raybould", "192": "Republican Deb Fischer", "193": "Democrat Chris Janicek", "194": "Republican Matt Innis", "195": "Republican Ben Sasse", "196": "Independent Steve Merrill", "197": "NH", "198": "Republican Donald Bolduc", "199": "Republican Bill O'Brien", "200": "Republican Bryant \"Corky\" Messner", "201": "Democrat Jeanne Shaheen", "202": "Independent Christine Todd Whitman", "203": "NJ", "204": "Democrat Bob Menendez", "205": "Republican Bob Hugin", "206": "Republican Hirsh Singh", "207": "Democrat Cory Booker", "208": "Libertarian Murray Sabrin", "209": "Green Party candidate Madelyn Hoffman", "210": "Economic Growth Party candidate Hank Schroeder", "211": "Independent Gary Johnson", "212": "NM", "213": "Democrat Martin Heinrich", "214": "Republican Mick Rich", "215": "Democrat Ben Ray Luj\u00e1n", "216": "Republican Gavin Clarkson", "217": "Republican Elisa Martinez", "218": "Democrat Tom Udall", "219": "Libertarian Gary Johnson", "220": "NV", "221": "Democrat Jacky Rosen", "222": "Republican Dean Heller", "223": "Libertarian Tim Hagan", "224": "Independent American Party candidate Kamau Bakari", "225": "None of the above", "226": "NY", "227": "Democrat Kirsten Gillibrand", "228": "Republican David Webber", "229": "OH", "230": "Democrat Sherrod Brown", "231": "Republican Jim Renacci", "232": "Green Party candidate Philena Farley", "233": "Independent Brad Henry", "234": "OK", "235": "Democrat Mike Workman", "236": "Democrat Dylan Billings", "237": "Republican Jim Inhofe", "238": "Independent Gordon Smith", "239": "OR", "240": "Republican Paul Romero", "241": "Democrat Jeff Merkley", "242": "PA", "243": "Democrat Bob Casey, Jr.", "244": "Republican Lou Barletta", "245": "Libertarian Dale Kerns", "246": "Green Party candidate Neal Gale", "247": "Independent Alan Fung", "248": "RI", "249": "Democrat Sheldon Whitehouse", "250": "Republican Robert Flanders", "251": "Democrat Jack Reed", "252": "Independent Jim Hodges", "253": "SC", "254": "Democrat Jaime Harrison", "255": "Republican Peggy Kandles", "256": "Democrat Gloria Bromell Tinubu", "257": "Republican Lindsey Graham", "258": "Independent Larry Pressler", "259": "SD", "260": "Democrat Dan Ahlers", "261": "Republican Scyller Borglum", "262": "Republican Mike Rounds", "263": "Independent Bob Corker", "264": "TN", "265": "Democrat Phil Bredesen", "266": "Republican Marsha Blackburn", "267": "Republican Bob Corker", "268": "Democrat James Mackler", "269": "Republican Bill Hagerty", "270": "Democrat Marquita Bradshaw", "271": "Republican Manny Sethi", "272": "Republican Josh Gapp", "273": "Republican Lamar Alexander", "274": "Independent Trudy Austin", "275": "Independent John Carico", "276": "Independent Dean Hill", "277": "Independent Jerry Patterson", "278": "TX", "279": "Democrat Beto O'Rourke", "280": "Republican Ted Cruz", "281": "Democrat Mary \"MJ\" Hegar", "282": "Republican Mark Yancey", "283": "Democrat Chris Bell", "284": "Democrat Amanda Edwards", "285": "Democrat Cristina Tzintzun Ramirez", "286": "Democrat Royce West", "287": "Republican John Cornyn", "288": "Libertarian Neal Dikeman", "289": "UT", "290": "Democrat Jenny Wilson", "291": "Republican Mitt Romney", "292": "Republican Orrin Hatch", "293": "Libertarian Craig Bowden", "294": "Independent Paul Trible", "295": "VA", "296": "Democrat Tim Kaine", "297": "Republican Corey Stewart", "298": "Republican Daniel Gade", "299": "Democrat Mark Warner", "300": "Libertarian Matt Waters", "301": "Independent Jim Douglas", "302": "VT", "303": "Democrat Bernie Sanders", "304": "Republican Brooke Paige", "305": "Independent Bernie Sanders", "306": "WA", "307": "Democrat Maria Cantwell", "308": "Republican Susan Hutchhison", "309": "WI", "310": "Democrat Tammy Baldwin", "311": "Republican Leah Vukmir", "312": "Independent Earl Ray Tomblin", "313": "WV", "314": "Democrat Joe Manchin", "315": "Republican Patrick Morrisey", "316": "Democrat Paula Swearengin", "317": "Republican Allen Whitt", "318": "Democrat Richard Ojeda", "319": "Republican Shelley Moore Capito", "320": "Independent Dave Freudenthal", "321": "WY", "322": "Democrat Gary Trauner", "323": "Republican John Barrasso", "324": "Democrat Yana Ludwig", "325": "Republican Liz Cheney", "326": "Republican Cynthia Lummis", "327": "Republican Dave Dodson", "328": "Republican Mike Enzi", "329": "Independent David Dodson"}, "geos": {"AK": "AK", "AL": "AL", "AR": "AR", "AZ": "AZ", "CA": "CA", "CO": "CO", "CT": "CT", "DE": "DE", "FL": "FL", "GA": "GA", "HI": "HI", "IA": "IA", "ID": "ID", "IL": "IL", "IN": "IN", "KS": "KS", "KY": "KY", "LA": "LA", "MA": "MA", "MD": "MD", "ME": "ME", "MI": "MI", "MN": "MN", "MO": "MO", "MS": "MS", "MT": "MT", "NC": "NC", "ND": "ND", "NE": "NE", "NH": "NH", "NJ": "NJ", "NM": "NM", "NV": "NV", "NY": "NY", "OH": "OH", "OK": "OK", "OR": "OR", "PA": "PA", "RI": "RI", "SC": "SC", "SD": "SD", "TN": "TN", "TX": "TX", "UT": "UT", "VA": "VA", "VT": "VT", "WA": "WA", "WI": "WI", "WV": "WV", "WY": "WY"}, "rand": 757626243}