{"districts": {"AZ": {"s": 0, "p1": 1, "d1": 2, "r1": 3, "i1": 4, "p3": 1, "d3": 5, "r3": 6, "i3": 7, "p4": 1, "d4": 5, "r4": 8, "i4": 7, "p5": 1, "d5": 5, "r5": 9, "i5": 7, "p6": 1, "d6": 5, "r6": 9, "i6": 7, "o1": 10, "o2": 11, "o3": 11, "o4": 11}, "CA": {"s": 12, "p1": 13, "d1": 14, "r1": 15, "i1": 14, "p3": 13, "d3": 5, "r3": 9, "i3": 16, "p4": 13, "d4": 5, "r4": 9, "i4": 16, "p5": 13, "d5": 5, "r5": 9, "i5": 16, "p6": 13, "d6": 5, "r6": 9, "i6": 16, "o1": 11, "o2": 11, "o3": 11, "o4": 11}, "CT": {"s": 17, "p1": 13, "d1": 18, "r1": 19, "i1": 18, "p3": 13, "d3": 5, "r3": 9, "i3": 16, "p4": 13, "d4": 5, "r4": 9, "i4": 16, "p5": 13, "d5": 5, "r5": 9, "i5": 16, "p6": 13, "d6": 5, "r6": 9, "i6": 16, "o1": 11, "o2": 11, "o3": 11, "o4": 11}, "DE": {"s": 20, "p1": 13, "d1": 21, "r1": 22, "i1": 21, "p3": 13, "d3": 23, "r3": 9, "i3": 16, "p4": 13, "d4": 5, "r4": 9, "i4": 16, "p5": 13, "d5": 5, "r5": 9, "i5": 16, "p6": 13, "d6": 5, "r6": 9, "i6": 16, "o1": 11, "o2": 11, "o3": 11, "o4": 11}, "FL": {"s": 24, "p1": 13, "d1": 25, "r1": 26, "i1": 25, "p3": 13, "d3": 5, "r3": 9, "i3": 16, "p4": 13, "d4": 5, "r4": 9, "i4": 16, "p5": 13, "d5": 5, "r5": 9, "i5": 16, "p6": 13, "d6": 5, "r6": 9, "i6": 16, "o1": 27, "o2": 11, "o3": 11, "o4": 11}, "HI": {"s": 28, "p1": 13, "d1": 29, "r1": 30, "i1": 29, "p3": 13, "d3": 5, "r3": 9, "i3": 16, "p4": 13, "d4": 5, "r4": 9, "i4": 16, "p5": 13, "d5": 5, "r5": 9, "i5": 16, "p6": 13, "d6": 5, "r6": 9, "i6": 16, "o1": 11, "o2": 11, "o3": 11, "o4": 11}, "IN": {"s": 31, "p1": 13, "d1": 32, "r1": 33, "i1": 32, "p3": 13, "d3": 5, "r3": 9, "i3": 16, "p4": 13, "d4": 5, "r4": 9, "i4": 16, "p5": 13, "d5": 5, "r5": 9, "i5": 16, "p6": 13, "d6": 5, "r6": 9, "i6": 16, "o1": 11, "o2": 11, "o3": 11, "o4": 11}, "MA": {"s": 34, "p1": 13, "d1": 35, "r1": 36, "i1": 35, "p3": 13, "d3": 5, "r3": 9, "i3": 16, "p4": 13, "d4": 5, "r4": 9, "i4": 16, "p5": 13, "d5": 5, "r5": 9, "i5": 16, "p6": 13, "d6": 5, "r6": 9, "i6": 16, "o1": 37, "o2": 38, "o3": 11, "o4": 11}, "MD": {"s": 39, "p1": 13, "d1": 40, "r1": 41, "i1": 40, "p3": 13, "d3": 5, "r3": 9, "i3": 16, "p4": 13, "d4": 5, "r4": 9, "i4": 16, "p5": 13, "d5": 5, "r5": 9, "i5": 16, "p6": 13, "d6": 5, "r6": 9, "i6": 16, "o1": 42, "o2": 11, "o3": 11, "o4": 11}, "ME": {"s": 43, "p1": 44, "d1": 45, "r1": 46, "i1": 45, "p3": 44, "d3": 5, "r3": 9, "i3": 47, "p4": 44, "d4": 5, "r4": 9, "i4": 47, "p5": 44, "d5": 5, "r5": 9, "i5": 47, "p6": 44, "d6": 5, "r6": 9, "i6": 47, "o1": 48, "o2": 49, "o3": 50, "o4": 11}, "MI": {"s": 51, "p1": 13, "d1": 52, "r1": 53, "i1": 52, "p3": 13, "d3": 5, "r3": 54, "i3": 16, "p4": 13, "d4": 5, "r4": 53, "i4": 16, "p5": 13, "d5": 5, "r5": 55, "i5": 16, "p6": 13, "d6": 5, "r6": 9, "i6": 16, "o1": 56, "o2": 11, "o3": 11, "o4": 11}, "MN": {"s": 57, "p1": 13, "d1": 58, "r1": 59, "i1": 58, "p2": 60, "d2": 61, "r2": 62, "i2": 11, "p3": 13, "d3": 5, "r3": 9, "i3": 16, "p4": 13, "d4": 5, "r4": 9, "i4": 16, "p5": 13, "d5": 5, "r5": 9, "i5": 16, "p6": 13, "d6": 5, "r6": 9, "i6": 16, "o1": 63, "o2": 11, "o3": 11, "o4": 64}, "MO": {"s": 65, "p1": 13, "d1": 66, "r1": 67, "i1": 66, "p3": 13, "d3": 5, "r3": 68, "i3": 16, "p4": 13, "d4": 5, "r4": 69, "i4": 16, "p5": 13, "d5": 5, "r5": 68, "i5": 16, "p6": 13, "d6": 5, "r6": 9, "i6": 16, "o1": 70, "o2": 71, "o3": 72, "o4": 11}, "MS": {"s": 73, "p1": 1, "d1": 74, "r1": 75, "i1": 75, "p2": 60, "d2": 76, "r2": 77, "i2": 11, "p3": 1, "d3": 78, "r3": 9, "i3": 7, "p4": 1, "d4": 5, "r4": 9, "i4": 7, "p5": 1, "d5": 5, "r5": 9, "i5": 7, "p6": 1, "d6": 79, "r6": 9, "i6": 7, "o1": 80, "o2": 81, "o3": 11, "o4": 11}, "MT": {"s": 82, "p1": 13, "d1": 83, "r1": 84, "i1": 83, "p3": 13, "d3": 5, "r3": 9, "i3": 16, "p4": 13, "d4": 5, "r4": 9, "i4": 16, "p5": 13, "d5": 5, "r5": 9, "i5": 16, "p6": 13, "d6": 5, "r6": 9, "i6": 16, "o1": 85, "o2": 86, "o3": 11, "o4": 11}, "ND": {"s": 87, "p1": 13, "d1": 88, "r1": 89, "i1": 88, "p3": 13, "d3": 5, "r3": 9, "i3": 16, "p4": 13, "d4": 5, "r4": 9, "i4": 16, "p5": 13, "d5": 5, "r5": 9, "i5": 16, "p6": 13, "d6": 5, "r6": 9, "i6": 16, "o1": 11, "o2": 11, "o3": 11, "o4": 11}, "NE": {"s": 90, "p1": 1, "d1": 91, "r1": 92, "i1": 92, "p3": 1, "d3": 5, "r3": 9, "i3": 7, "p4": 1, "d4": 5, "r4": 9, "i4": 7, "p5": 1, "d5": 5, "r5": 9, "i5": 7, "p6": 1, "d6": 5, "r6": 9, "i6": 7, "o1": 11, "o2": 11, "o3": 11, "o4": 11}, "NJ": {"s": 93, "p1": 13, "d1": 94, "r1": 95, "i1": 94, "p3": 13, "d3": 5, "r3": 9, "i3": 16, "p4": 13, "d4": 5, "r4": 9, "i4": 16, "p5": 13, "d5": 5, "r5": 9, "i5": 16, "p6": 13, "d6": 5, "r6": 9, "i6": 16, "o1": 96, "o2": 11, "o3": 11, "o4": 11}, "NM": {"s": 97, "p1": 13, "d1": 98, "r1": 99, "i1": 98, "p3": 13, "d3": 5, "r3": 9, "i3": 16, "p4": 13, "d4": 5, "r4": 9, "i4": 16, "p5": 13, "d5": 5, "r5": 9, "i5": 16, "p6": 13, "d6": 5, "r6": 9, "i6": 16, "o1": 11, "o2": 11, "o3": 11, "o4": 11}, "NV": {"s": 100, "p1": 1, "d1": 101, "r1": 102, "i1": 102, "p3": 1, "d3": 5, "r3": 9, "i3": 7, "p4": 1, "d4": 5, "r4": 9, "i4": 7, "p5": 1, "d5": 5, "r5": 9, "i5": 7, "p6": 1, "d6": 5, "r6": 9, "i6": 7, "o1": 11, "o2": 11, "o3": 11, "o4": 11}, "NY": {"s": 103, "p1": 13, "d1": 104, "r1": 105, "i1": 104, "p3": 13, "d3": 5, "r3": 9, "i3": 16, "p4": 13, "d4": 5, "r4": 9, "i4": 16, "p5": 13, "d5": 5, "r5": 9, "i5": 16, "p6": 13, "d6": 5, "r6": 9, "i6": 16, "o1": 11, "o2": 11, "o3": 11, "o4": 11}, "OH": {"s": 106, "p1": 13, "d1": 107, "r1": 108, "i1": 107, "p3": 13, "d3": 5, "r3": 9, "i3": 16, "p4": 13, "d4": 5, "r4": 9, "i4": 16, "p5": 13, "d5": 5, "r5": 9, "i5": 16, "p6": 13, "d6": 5, "r6": 9, "i6": 16, "o1": 109, "o2": 11, "o3": 11, "o4": 11}, "PA": {"s": 110, "p1": 13, "d1": 111, "r1": 112, "i1": 111, "p3": 13, "d3": 5, "r3": 9, "i3": 16, "p4": 13, "d4": 5, "r4": 9, "i4": 16, "p5": 13, "d5": 5, "r5": 113, "i5": 16, "p6": 13, "d6": 5, "r6": 9, "i6": 16, "o1": 114, "o2": 11, "o3": 11, "o4": 11}, "RI": {"s": 115, "p1": 13, "d1": 116, "r1": 117, "i1": 116, "p3": 13, "d3": 5, "r3": 9, "i3": 16, "p4": 13, "d4": 5, "r4": 9, "i4": 16, "p5": 13, "d5": 5, "r5": 9, "i5": 16, "p6": 13, "d6": 5, "r6": 9, "i6": 16, "o1": 11, "o2": 11, "o3": 11, "o4": 11}, "TN": {"s": 118, "p1": 1, "d1": 119, "r1": 120, "i1": 121, "p3": 1, "d3": 5, "r3": 9, "i3": 7, "p4": 1, "d4": 5, "r4": 9, "i4": 7, "p5": 1, "d5": 5, "r5": 9, "i5": 7, "p6": 1, "d6": 5, "r6": 9, "i6": 7, "o1": 11, "o2": 11, "o3": 11, "o4": 11}, "TX": {"s": 122, "p1": 1, "d1": 123, "r1": 124, "i1": 124, "p3": 1, "d3": 5, "r3": 9, "i3": 7, "p4": 1, "d4": 5, "r4": 9, "i4": 7, "p5": 1, "d5": 5, "r5": 9, "i5": 7, "p6": 1, "d6": 5, "r6": 9, "i6": 7, "o1": 11, "o2": 11, "o3": 11, "o4": 11}, "UT": {"s": 125, "p1": 1, "d1": 126, "r1": 127, "i1": 128, "p3": 1, "d3": 5, "r3": 9, "i3": 7, "p4": 1, "d4": 5, "r4": 9, "i4": 7, "p5": 1, "d5": 5, "r5": 9, "i5": 7, "p6": 1, "d6": 5, "r6": 9, "i6": 7, "o1": 129, "o2": 130, "o3": 131, "o4": 11}, "VA": {"s": 132, "p1": 13, "d1": 133, "r1": 134, "i1": 133, "p3": 13, "d3": 5, "r3": 9, "i3": 16, "p4": 13, "d4": 5, "r4": 9, "i4": 16, "p5": 13, "d5": 5, "r5": 9, "i5": 16, "p6": 13, "d6": 5, "r6": 9, "i6": 16, "o1": 135, "o2": 11, "o3": 11, "o4": 11}, "VT": {"s": 136, "p1": 44, "d1": 137, "r1": 138, "i1": 137, "p3": 44, "d3": 5, "r3": 9, "i3": 47, "p4": 44, "d4": 5, "r4": 9, "i4": 47, "p5": 44, "d5": 5, "r5": 9, "i5": 47, "p6": 44, "d6": 5, "r6": 9, "i6": 47, "o1": 11, "o2": 11, "o3": 11, "o4": 11}, "WA": {"s": 139, "p1": 13, "d1": 140, "r1": 141, "i1": 140, "p3": 13, "d3": 5, "r3": 9, "i3": 16, "p4": 13, "d4": 5, "r4": 9, "i4": 16, "p5": 13, "d5": 5, "r5": 9, "i5": 16, "p6": 13, "d6": 5, "r6": 9, "i6": 16, "o1": 11, "o2": 11, "o3": 11, "o4": 11}, "WI": {"s": 142, "p1": 13, "d1": 143, "r1": 144, "i1": 143, "p3": 13, "d3": 5, "r3": 9, "i3": 16, "p4": 13, "d4": 5, "r4": 9, "i4": 16, "p5": 13, "d5": 5, "r5": 9, "i5": 16, "p6": 13, "d6": 5, "r6": 9, "i6": 16, "o1": 145, "o2": 11, "o3": 11, "o4": 11}, "WV": {"s": 146, "p1": 13, "d1": 147, "r1": 148, "i1": 147, "p3": 13, "d3": 5, "r3": 9, "i3": 16, "p4": 13, "d4": 5, "r4": 9, "i4": 16, "p5": 13, "d5": 5, "r5": 9, "i5": 16, "p6": 13, "d6": 5, "r6": 9, "i6": 16, "o1": 11, "o2": 11, "o3": 11, "o4": 11}, "WY": {"s": 149, "p1": 1, "d1": 150, "r1": 151, "i1": 151, "p3": 1, "d3": 5, "r3": 9, "i3": 7, "p4": 1, "d4": 5, "r4": 9, "i4": 7, "p5": 1, "d5": 5, "r5": 9, "i5": 7, "p6": 1, "d6": 5, "r6": 9, "i6": 7, "o1": 152, "o2": 11, "o3": 11, "o4": 11}}, "values": {"0": "AZ", "1": "R", "2": "Democrat Kyrsten Sinema", "3": "Republican Martha McSally", "4": "Republican Jeff Flake", "5": "A Democratic Candidate", "6": "Republican Kelli Ward", "7": "Republican _none_", "8": "Republican Joe Arpaio", "9": "A Republican Candidate", "10": "Libertarian Doug Marks", "11": "_none_", "12": "CA", "13": "D", "14": "Democrat Dianne Feinstein", "15": "Democrat Kevin de Le\u00f3n", "16": "Democrat _none_", "17": "CT", "18": "Democrat Chris Murphy", "19": "Republican Matthew Corey", "20": "DE", "21": "Democrat Tom Carper", "22": "Republican Gene Truono", "23": "Democrat Kerri Evelyn Harris", "24": "FL", "25": "Democrat Bill Nelson", "26": "Republican Rick Scott", "27": "Libertarian Joe Wendt", "28": "HI", "29": "Democrat Mazie Hirono", "30": "Republican Thomas White", "31": "IN", "32": "Democrat Joe Donnelly", "33": "Republican Mike Braun", "34": "MA", "35": "Democrat Elizabeth Warren", "36": "Republican Geoff Diehl", "37": "Independent John Devine", "38": "Independent Shiva Ayyadurai", "39": "MD", "40": "Democrat Ben Cardin", "41": "Republican Tony Campbell", "42": "Libertarian Arvin Vohra", "43": "ME", "44": "I", "45": "Independent Angus King", "46": "Republican Eric Brakey", "47": "Independent _none_", "48": "Democrat Zak Ringelstein", "49": "Independent Benjamin Pollard", "50": "Libertarian Chris Lyons", "51": "MI", "52": "Democrat Debbie Stabenow", "53": "Republican John James", "54": "Republican Bob Carr", "55": "Republican Sandy Pensler", "56": "Independent Marcia Squier", "57": "MN", "58": "Democrat Amy Klobuchar", "59": "Republican Jim Newberger", "60": "none", "61": "Democrat Tina Smith", "62": "Republican Karin Housley", "63": "Green Party candidate Paula Overby", "64": "Independent Jerry Trooien", "65": "MO", "66": "Democrat Claire McCaskill", "67": "Republican Josh Hawley", "68": "Republican Courtland Sykes", "69": "Republican Austin Petersen", "70": "Green Party candidate Jerome Bauer", "71": "Libertarian Japheth Campbell", "72": "Independent Craig O'Dear", "73": "MS", "74": "Democrat David Baria", "75": "Republican Roger Wicker", "76": "Democrat Mike Espy", "77": "Republican Cindy Hyde-Smith", "78": "Democrat Howard Sherman", "79": "Democrat Chris McDaniel", "80": "Libertarian Danny Bedwell", "81": "Reform party candidate Shawn O'Hara", "82": "MT", "83": "Democrat Jon Tester", "84": "Republican Matt Rosendale", "85": "Green Party candidate Timothy Adams", "86": "Libertarian Rick Breckenridge", "87": "ND", "88": "Democrat Heidi Heitkamp", "89": "Republican Kevin Cramer", "90": "NE", "91": "Democrat Jane Raybould", "92": "Republican Deb Fischer", "93": "NJ", "94": "Democrat Bob Menendez", "95": "Republican Bob Hugin", "96": "Libertarian Murray Sabrin", "97": "NM", "98": "Democrat Martin Heinrich", "99": "Republican Mick Rich", "100": "NV", "101": "Democrat Jacky Rosen", "102": "Republican Dean Heller", "103": "NY", "104": "Democrat Kirsten Gillibrand", "105": "Republican David Webber", "106": "OH", "107": "Democrat Sherrod Brown", "108": "Republican Jim Renacci", "109": "Green Party candidate Philena Farley", "110": "PA", "111": "Democrat Bob Casey, Jr.", "112": "Republican Lou Barletta", "113": "Republican Jim Christiana", "114": "Libertarian Dale Kerns", "115": "RI", "116": "Democrat Sheldon Whitehouse", "117": "Republican Robert Flanders", "118": "TN", "119": "Democrat Phil Bredesen", "120": "Republican Marsha Blackburn", "121": "Republican Bob Corker", "122": "TX", "123": "Democrat Beto O'Rourke", "124": "Republican Ted Cruz", "125": "UT", "126": "Democrat Jenny Wilson", "127": "Republican Mitt Romney", "128": "Republican Orrin Hatch", "129": "Libertarian Craig Bowden", "130": "Constitution Party candidate Tim Aalders", "131": "Independent American Party candidate Reed McCandless", "132": "VA", "133": "Democrat Tim Kaine", "134": "Republican Corey Stewart", "135": "Libertarian Matt Waters", "136": "VT", "137": "Independent Bernie Sanders", "138": "Republican Brooke Paige", "139": "WA", "140": "Democrat Maria Cantwell", "141": "Republican Susan Hutchhison", "142": "WI", "143": "Democrat Tammy Baldwin", "144": "Republican Leah Vukmir", "145": "Veterans Party of American candidate Joseph Schnering", "146": "WV", "147": "Democrat Joe Manchin", "148": "Republican Patrick Morrisey", "149": "WY", "150": "Democrat Gary Trauner", "151": "Republican John Barrasso", "152": "Independent David Dodson"}, "geos": {"AZ": "AZ", "CA": "CA", "CT": "CT", "DE": "DE", "FL": "FL", "HI": "HI", "IN": "IN", "MA": "MA", "MD": "MD", "ME": "ME", "MI": "MI", "MN": "MN", "MO": "MO", "MS": "MS", "MT": "MT", "ND": "ND", "NE": "NE", "NJ": "NJ", "NM": "NM", "NV": "NV", "NY": "NY", "OH": "OH", "PA": "PA", "RI": "RI", "TN": "TN", "TX": "TX", "UT": "UT", "VA": "VA", "VT": "VT", "WA": "WA", "WI": "WI", "WV": "WV", "WY": "WY"}, "rand": 570765414}